Workbook
Name Accrued_Physical: [2]ImpAnalysis!$I$26
Name Actual_Age: [2]Inputs!$C$159
Name Actual_Taxes: [2]Tax!$G$21
Name Adj_Pro_Assessed_Val: [2]Tax!$K$12
Name AdjCatNo: '[2]IS Grid'!$A$81
Name Ambient_Area: [2]Inputs!$C$96
Name AmtBdgt: [3]OpActuals!$I:$I
Name AMTY1: [3]OpActuals!$C:$C
Name AMTY2: [3]OpActuals!$D:$D
Name AMTY3: [3]OpActuals!$E:$E
Name AMTY4: [3]OpActuals!$F:$F
Name AMTY5: [3]OpActuals!$H:$H
Name AnalysisType: [4]Assumptions!$C$2:$C$3
Name Anchor_1_Name: [2]Inputs!$C$119
Name Anchor_1_SF: [2]Inputs!$C$120
Name Anchor_2_Name: [2]Inputs!$C$121
Name Anchor_2_SF: [2]Inputs!$C$122
Name Anchor_3_Name: [2]Inputs!$C$123
Name Anchor_3_SF: [2]Inputs!$C$124
Name Anchor_4_Name: [2]Inputs!$C$125
Name Anchor_4_SF: [2]Inputs!$C$126
Name Anchor_5_Name: [2]Inputs!$C$127
Name Anchor_5_SF: [2]Inputs!$C$128
Name Anchor_6_Name: [2]Inputs!$C$129
Name Anchor_6_SF: [2]Inputs!$C$130
Name Annual_Mkt_Rent: '[2]Mkt Rent'!$BE$85
Name Appraisal_Fee: [2]Inputs!$C$58
Name Appraiser: [2]Inputs!$C$9
Name Apt.Concessions: '[2]Dir Cap'!$H$8
Name Apt.Concessions.Percent: '[2]Dir Cap'!$E$8
Name Apt.LosstoLease: '[2]Dir Cap'!$H$7
Name Apt.LosstoLease.Percent: '[2]Dir Cap'!$E$7
Name Apt_Row_Cost: [2]Cost!#REF!
Name ARC.Homesites: '[1]ARC Financials'!$F$240
Name ARC.No: [1]Instructions!$B$3
Name ARC.PropAddress: '[1]ARC Property List'!$D$9:$D$67
Name ARC.PropCity: '[1]ARC Property List'!$E$9:$E$67
Name ARC.PropCode: '[1]ARC Property List'!$B$9:$B$67
Name ARC.PropName: '[1]ARC Property List'!$C$9:$C$67
Name ARC.PropState: '[1]ARC Property List'!$F$9:$F$67
Name ARC.PropZip: '[1]ARC Property List'!$G$9:$G$67
Name ARI: '[2]Dir Cap'!$H$9
Name ArrTot: [6]Assumptions!$F$9:$G$21
Name ArrTotal: [4]Assumptions!$F$9:$G$21
Name As_Is_Value: [2]Values!$M$21
Name bbDateOfValueEffectiveDate: '[7]Valuation Scenarios'!$D$85
Name bbDateReport: [7]Assignment!$B$44
Name bbMarketValues: '[7]Valuation Scenarios'!$D$76
Name bbPropertyOwner: [7]Assignment!$B$27
Name bbValuationType: '[7]Valuation Scenarios'!$D$79
Name bbValueConditionScen1: '[3]Valuation Scenarios'!$B$8
Name bbValueDateScen1: '[3]Valuation Scenarios'!$B$5
Name bbValueInterestScen1: '[3]Valuation Scenarios'!$B$7
Name bbValueNameScen1: '[3]Valuation Scenarios'!$B$4
Name Building_Area: [2]Inputs!$C$146
Name Building_Class_List: [2]InputsRangeNames!$J$4:$J$8
Name Building_Class_Value: [2]InputsRangeNames!$J$2
Name Building_Class_Value_List: [2]InputsRangeNames!$I$4:$I$8
Name caDeferredMaint: [3]Cost!$F$44
Name caLandValueRND: [3]LSaleAdj!$E$48

Sheet Property Info
A1: Account | B1: R0118932 | G1: Fill in Highlighted Fields
A2: Occ. Code | B2: 407 | G2: DO NOT UPDATE CELLS IN THIS BOX
A3: Number of Buildings | B3: 1
A4: GBA | B4: 187720
A5: Footprint | B5: 33950
A6: NRA | B6: 33750
A7: SF Basis | B7: GBA | C7: ←Dropdown | E7: GBA | F7: Gross Building Area
A8: Year Built | B8: 1999 | E8: NRA | F8: Net Renatable Area
A9: Condition | B9: Average | E9: GLA | F9: Gross Leasable Area
A10: Year/Condition | B10: 1999/Average
A11: Site Size | B11: 108316
A12: Acres | B12: =B11/43560
A13: Coverage Ratio | B13: =B5/B11
A14: Office % | B14: 0.052
A15: Type | B15: Distribution Warehouse
A16: Address | B16: 6245 Washington Street
A17: City | B17: Unincorporated Adams County, CO
A18: County | B18: Adams County
A19: Assumed Occupancy | B19: 1
A20: Assessor's Assigned Value | B20: 3916200
A21: Petitioner's Value | B21: 3060000
A22: Recent Sale Date | B22: 42675
A23: Recent Sale Price | B23: 2880000
A24: Sale Type | B24: Investment
A25: Value Premise | B25: Fee Simple
A26: Date of Value | B26: 44012
A27: Report Date | B27: 45127
A28: Hearing Date | B28: 45192
A29: Zoning | B29: I-1 (Light Industrial)
A30: Zoning Authority | B30: Adams County

Sheet FE
A1: Note: | B1: FILL ONLY HIGHLIGHTED CELLS
B3: EXECUTIVE SUMMARY
B4: Account Number | C4: ='Property Info'!B1
B5: Address | C5: ='Property Info'!B16
B6: County | C6: ='Property Info'!B18
B7: City, State | C7: ='Property Info'!B17
B8: Effective Date | C8: ='Property Info'!B26
B9: Appraisal Date | C9: ='Property Info'!B27
B10: Hearing Date | C10: ='Property Info'!B28
B12: Property Type | C12: ='Property Info'!B15
B13: Property Size
B14: ='Property Info'!B7 | C14: =IF(B14="GBA", 'Property Info'!B4,IF(B14="NRA",'Property Info'!B6,'Property Info'!B4))
B15: Number of Buildings | C15: ='Property Info'!B3
B16: Year Built/Condition | C16: ='Property Info'!B10
B17: Condition | C17: Average
B18: Site Size (SF) | C18: ='Property Info'!B11
B19: Property Rights Appraised | C19: ='Property Info'!B25
B20: Assumed Occupancy | C20: ='Property Info'!B19
B21: Stabilized Occupancy | C21: ='Income Approach'!D22
D23: PETITION SCENARIO
E24: $ | F24: $/SF
D25: Assessor's Assigned Value | E25: ='Basic Sales Grid'!D51 | F25: =E25/C14
D26: Petitioner’s Requested Value | E26: ='Basic Sales Grid'!D52 | F26: =E26/C14
G28: APPRAISAL INFORMATION
G29: Intended User | H29: Adams County Board of Equalization, Adams County Attorney, Colorado Board of Assessment Appeals
H30: =clCompanyAddressStreet1&", "&clCompanyAddressStreet2
H31: =clCompanyAddressCity&", "&clCompanyAddressState&" "&clCompanyAddressZip
G32: Intended User(s) | H32: =H29
G33: Intended Use | H33: Aid in tax appeal decision
G34: Values Concluded | H34: Retrospective Market Value
G35: Property Rights Appraised / Premise | H35: Retrospective Market Value of the Fee Simple interest in the subject property, As Is as of June 30, 2020
G36: Premise Summary | H36: Retrospective Market Value As Is - June 30, 2020
G37: Date of Inspection | H37: 45079
G38: Report Date | H38: ='Property Info'!B27
G39: Marketing Time | H39: 12 months
G40: Exposure Time | H40: 12 months
G41: Owner of Record
G42: Property Contact(s) | H42: Mr. Patrick de Jongh and Mr. Michael Kaufman, taxpayer representatives, were interviewed by phone and email throughout the appraisal process and intended our inspection of the subject property.
G43: Most Probable Purchaser | H43: =pdMostProbablePurchaser
G44: Highest and Best Use
G45: If Vacant | H45: Light Industrial Development
G46: As Improved | H46: =pdHBUAsImproved
M49: SCOPE OF THE INVESTIGATION
M50: General and Market Data Analyzed | N50: § Regional economic data and trends
N51: § Market analysis data specific to the subject property type
N52: § Published survey data
N53: § Neighborhood demographic data
N54: § Comparable cost, sale, rental, expense, and capitalization rate data
N55: § Floodplain status
N56: § Zoning information
N57: § Assessor’s information
N58: § Interviewed professionals knowledgeable about the subject’s property type and market
M59: Inspection Details | N59: The interior and exterior of the subject was inspected.
M60: Data Sources
M61: Site Size | N61: Adams County Assessor Records, Appraiser Measurement
M62: Building Size | N62: Adams County Assessor Records, Appraiser Measurement
M63: Zoning information | N63: Adams County Planning Department
M64: Flood Status | N64: FEMA Flood Map Service Center
M65: Demographics | N65: CoStar Market Reports
M66: Land Sales | N66: CoStar, MLS, Adams County Sales Data, Local Brokers
M67: Cost Estimate Data | N67: Marshall & Swift Cost Estimator
M68: Comparable Improved Sales | N68: CoStar, MLS, Adams County Sales Data, Local Brokers
M69: Comparable Improved Rents | N69: CoStar, MLS, Adams County Lease Data, Local Brokers
M70: Property Specific Data Requested and Received
N71: Lease, Lease Addendum
N72: Estimated financial analysis
N73: Property Expenses (2019, 2020)
M75: Data Requested, but not Provided
N76: Rent Roll
N77: Building Plans
N78: Environmental survey
N79: ALTA Survey
R81: EXTRAORDINARY ASSUMPTION(S) AND HYPOTHETICAL CONDITION(S)
R82: The values presented within this appraisal report are subject to the extraordinary assumptions and hypothetical conditions listed below. Pursuant to the requirement within Uniform Standards of Professional Appraisal Practice Standards, it is stated here that the use of any extraordinary assumptions might have affected the assignment results.
R83: Extraordinary Assumption(s)
A84: =IF(R84="","X","") | Q84: 1 | R84: This appraisal employs no extroidinary assumptions.
A85: =IF(R85="","X","") | Q85: 2 | R85: =IFERROR(IF(INDEX([14]!TableCondLang[#Data],MATCH($E85,[14]!TableCondLang[Row_Num],0),COLUMN([14]!TableCondLang[Discriminator])-1)="Extraordinary",INDEX([14]!TableCondLang[#Data],MATCH($E85,[14]!TableCondLang[Row_Num],0),COLUMN([14]!TableCondLang[Description])-1),""),"")
A86: =IF(R86="","X","") | Q86: 3 | R86: =IFERROR(IF(INDEX([14]!TableCondLang[#Data],MATCH($E86,[14]!TableCondLang[Row_Num],0),COLUMN([14]!TableCondLang[Discriminator])-1)="Extraordinary",INDEX([14]!TableCondLang[#Data],MATCH($E86,[14]!TableCondLang[Row_Num],0),COLUMN([14]!TableCondLang[Description])-1),""),"")
A87: =IF(R87="","X","") | Q87: 4 | R87: =IFERROR(IF(INDEX([14]!TableCondLang[#Data],MATCH($E87,[14]!TableCondLang[Row_Num],0),COLUMN([14]!TableCondLang[Discriminator])-1)="Extraordinary",INDEX([14]!TableCondLang[#Data],MATCH($E87,[14]!TableCondLang[Row_Num],0),COLUMN([14]!TableCondLang[Description])-1),""),"")
A88: =IF(S88="","X","") | S88: =IFERROR(IF(INDEX([14]!TableCondLang[#Data],MATCH($E88,[14]!TableCondLang[Row_Num],0),COLUMN([14]!TableCondLang[Discriminator])-1)="Extraordinary",INDEX([14]!TableCondLang[#Data],MATCH($E88,[14]!TableCondLang[Row_Num],0),COLUMN([14]!TableCondLang[Description])-1),""),"")
A89: =IF(S89="","X","") | R89: Hypothetical Condition(s) | S89: =IFERROR(IF(INDEX([14]!TableCondLang[#Data],MATCH($E89,[14]!TableCondLang[Row_Num],0),COLUMN([14]!TableCondLang[Discriminator])-1)="Extraordinary",INDEX([14]!TableCondLang[#Data],MATCH($E89,[14]!TableCondLang[Row_Num],0),COLUMN([14]!TableCondLang[Description])-1),""),"")
A90: =IF(R90="","X","") | Q90: 1 | R90: This appraisal employs no hypothetical conditions.
A91: =IF(R91="","X","") | Q91: 2 | R91: =IFERROR(IF(INDEX([14]!TableCondLang[#Data],MATCH($E91,[14]!TableCondLang[Row_Num],0),COLUMN([14]!TableCondLang[Discriminator])-1)="Extraordinary",INDEX([14]!TableCondLang[#Data],MATCH($E91,[14]!TableCondLang[Row_Num],0),COLUMN([14]!TableCondLang[Description])-1),""),"")
A92: =IF(R92="","X","") | Q92: 3 | R92: =IFERROR(IF(INDEX([14]!TableCondLang[#Data],MATCH($E92,[14]!TableCondLang[Row_Num],0),COLUMN([14]!TableCondLang[Discriminator])-1)="Extraordinary",INDEX([14]!TableCondLang[#Data],MATCH($E92,[14]!TableCondLang[Row_Num],0),COLUMN([14]!TableCondLang[Description])-1),""),"")
A93: =IF(R93="","X","") | Q93: 4 | R93: =IFERROR(IF(INDEX([14]!TableCondLang[#Data],MATCH($E93,[14]!TableCondLang[Row_Num],0),COLUMN([14]!TableCondLang[Discriminator])-1)="Extraordinary",INDEX([14]!TableCondLang[#Data],MATCH($E93,[14]!TableCondLang[Row_Num],0),COLUMN([14]!TableCondLang[Description])-1),""),"")
A94: =IF(R94="","X","") | R94: =IFERROR(IF(INDEX([14]!TableCondLang[#Data],MATCH($E94,[14]!TableCondLang[Row_Num],0),COLUMN([14]!TableCondLang[Discriminator])-1)="Extraordinary",INDEX([14]!TableCondLang[#Data],MATCH($E94,[14]!TableCondLang[Row_Num],0),COLUMN([14]!TableCondLang[Description])-1),""),"")
T95: PROPERTY OVERVIEW
T96: Property Name | U96: Single-Tenant Industrial Building
T97: Address | U97: ='Property Info'!B16
U98: ='Property Info'!B17
T99: Location | U99: North side of West 62nd Avenue, west of Washington Street, in unincorporated Adams County, Colorado.
T100: Property Description | U100: =U96
T101: and | U101: ='[7]Improvement Description_2'!C31&" ("&'[7]Improvement Description_2'!C32&") "&'[7]Improvement Description_2'!C33
T102: County | U102: ='Property Info'!B18
T103: Account Number(s) | U103: ='Property Info'!B1
T104: Note: | U104: Property has a mailing address for the City of Denver, but is located in unincorporated Adams County and is governed by County regulations.
T105: Census Tract No. | U105: =pdCensusTract
T106: Legal Description | U106: SUB:SAL LOT:1
T107: Site Area
T108: Primary Site | U108: ='Property Info'!B11 | V108: =U108/43560
...

Sheet Market Neighborhood
B2: MARKET DATA
B3: Surrounding Area | C3: Industrial | D3: Market Trend | E3: Growth
B4: Overall Real Estate Values | C4: Increasing | D4: Neighborhood Vacancy | E4: 0.053
B5: Predominant Property Use(s) | C5: Industrial Neighborhood Retail Lodging | D5: Estimated Marketing | E5: 12 months
D6: Estimated Exposure | E6: 12 months
B7: Market Subsector(s) | C7: Adams County | D7: Q1 2019-Q2 2020 | F7: ←Change this
B8: Vacancy - CoStar - Industrial 20,000 SF-50,000 SF | D8: 0.07 | F8: ←From Income
C9: Denver CBSA | D9: =D7 | F9: ←Change This
B10: Vacancy - CoStar - Industrial 20,000 SF-50,000 SF | D10: 0.043 | F10: ←From Income
F11: NEIGHBORHOOD DATA
F12: Market Area Comments | G12: The subject property is located north of East 62nd Avenue, approximately 289 feet west of Washington Street, in unincorporated Adams County, Colorado. The immediate area is developed with light to medium intensity industrial properties, similar to the subject. The majority of the area is zoned I-1 (Light Industrial), allowing for warehousing, storage, distribution, and light-intensity industrial activity. A visual inspection the neighborhood indicates significant new development and redevelopment over the past five years. Local street/sidewalk infrastructure and municipal services have also been updated over that time.
F13: Surrounding Uses | G13: North: | H13: Industrial Lots
G14: South: | H14: Light Industrial
G15: East: | H15: Industrial Storage Lot
G16: West: | H16: Light Industrial
F17: Property Contact Interview | G17: =clInspectionContactName
I18: CHANGE → | J18: Average Sale Price - Denver Market Industrial - 10,000 SF-50,000 SF | N18: Average Sale Price - Adams County Industrial - 10,000 SF-50,000 SF
J19: Period | K19: Avg. Price ($/SF) | L19: % Change - Q2 2020 | M19: ←CHANGE → | N19: Period | O19: Avg. Price ($/SF) | P19: % Change - Q2 2020
I20: Pase from CoStar→ | J20: 2023 Q2 QTD | K20: 147 | N20: 2023 Q2 QTD | O20: 147
J21: 2023 Q1 | K21: 143 | L21: =($C$18-K21)/K21 | N21: 2023 Q1 | O21: 143
J22: 2022 Q4 | K22: 142 | L22: =($C$18-K22)/K22 | N22: 2022 Q4 | O22: 142
J23: 2022 Q3 | K23: 141 | L23: =($C$18-K23)/K23 | N23: 2022 Q3 | O23: 141
J24: 2022 Q2 | K24: 139 | L24: =($C$18-K24)/K24 | N24: 2022 Q2 | O24: 139
J25: 2022 Q1 | K25: 138 | L25: =($C$18-K25)/K25 | N25: 2022 Q1 | O25: 138
J26: 2021 Q4 | K26: 137 | L26: =($C$18-K26)/K26 | N26: 2021 Q4 | O26: 137
J27: 2021 Q3 | K27: 136 | L27: =($C$18-K27)/K27 | N27: 2021 Q3 | O27: 136
J28: 2021 Q2 | K28: 135 | L28: =($C$18-K28)/K28 | N28: 2021 Q2 | O28: 135
J29: 2021 Q1 | K29: 134 | L29: =($C$18-K29)/K29 | N29: 2021 Q1 | O29: 134
J30: 2020 Q4 | K30: 132 | L30: =($C$18-K30)/K30 | N30: 2020 Q4 | O30: 132
J31: 2020 Q3 | K31: 131 | L31: =($C$18-K31)/K31 | N31: 2020 Q3 | O31: 131
J32: 2020 Q2 | K32: 130 | L32: =($C$18-K32)/K32 | N32: 2020 Q2 | O32: 130
J33: 2020 Q1 | K33: 129 | L33: =($C$18-K33)/K33 | N33: 2020 Q1 | O33: 129 | P33: =($G$18-O33)/O33
J34: 2019 Q4 | K34: 128 | L34: =($C$18-K34)/K34 | N34: 2019 Q4 | O34: 128 | P34: =($G$18-O34)/O34
J35: 2019 Q3 | K35: 127 | L35: =($C$18-K35)/K35 | N35: 2019 Q3 | O35: 127 | P35: =($G$18-O35)/O35
J36: 2019 Q2 | K36: 125 | L36: =($C$18-K36)/K36 | N36: 2019 Q2 | O36: 125 | P36: =($G$18-O36)/O36
J37: 2019 Q1 | K37: 124 | L37: =($C$18-K37)/K37 | N37: 2019 Q1 | O37: 124 | P37: =($G$18-O37)/O37

Sheet Site Information
B2: SITE DESCRIPTION OVERVIEW
B4: Location | C4: =FE!U99
B5: Account Number | C5: =FE!U103
B6: Legal Description | C6: =FE!U106
B7: Site Area
B8: Primary Site | C8: =FE!U108 | D8: =FE!V108
B9: Excess Land | C9: =FE!U109 | D9: =FE!V109
B10: Surplus Land | C10: =FE!U110 | D10: =FE!V110
B11: Total | C11: =FE!U111 | D11: =FE!V111
B12: Configuration | C12: Generally rectangular site with street access from West 62nd Avenue and Washington St., via an apparent access easement with the adjacent property to the east.
B13: Topography | C13: Generally Level
B14: Drainage | C14: Appears adequate
B15: Utilities/Municipal Services | C15: Typical utilities and municipal services available to site.
B16: Floodplain | C16: Zone | D16: Map | E16: Date
C17: Zone X (Unshaded) | D17: 08001C0333H | E17: 39146 | I17: Zone A | J17: Zone X (Shaded)
C18: Zone X (unshaded) is a Non-Special Flood Hazard Area (NSFHA) of minimal flood hazard, usually depicted on Flood Insurance Rate Maps (FIRM) as above the 500-year flood level. This is an area in a low to moderate risk flood zone that is not in any immediate danger from flooding caused by overflowing rivers or hard rains. In communities that participate in the National Flood Insurance Program (NFIP), flood insurance is available to all property owners and renters in this zone.
B19: Census Tract No. | C19: =pdCensusTract
B21: SITE DESCRIPTION OVERVIEW - CONTINUED
B22: Soil/Subsoil Conditions | C22: We did not receive nor review a soil report. However, we assume that the soil's load-bearing capacity is sufficient to support existing structure(s). We did not observe any evidence to the contrary during our physical inspection of the property.
B23: Environmental Concerns | C23: No unusual conditions observed. No studies provided. Site is assumed to be free of any environmental concerns.
B24: Land Use Restrictions | C24: No atypical easements or encumbrances noted. Typical access easement appears to exist along the north boundary of the adjacent property to the east, providing access to the subject from Washington Street. Signage directs deliveries to access the subject from noted access road.
B25: Hazards Nuisances | C25: None noted
B26: Frontage | C26: West 62nd Avenue
B27: Access | C27: West 62nd Avenue (direct), Washington Street (via apparent access easement to the east)
B28: Visibility | C28: Unobstructed: West 62nd Ave. Obstructed: Washington Street - through adjacent parcel.
B29: Surrounding Land Uses | C29: Light to medium-intensity industrial
B30: Enterprise Zone | C30: None noted
B31: Traffic Counts | C31: West 62nd Ave: 5,235 VPD, Washington Street: 13,501 VPD Per CoStar (Jan. 2022 Est.)
B32: Transportation Facilities | C32: Northbound and southbound bus stops located along Washington Street, at E. 62nd Ave.
B33: Comments | C33: Light industrial property located in an area of generally similar industrial development. Access to the property available from E. 62nd Ave. and Washington St. with visibility available from both thoroughfares. Convenient access to Interstate 25, Interstate 76, and Interstate 270, all less than one mile from the subject property. No atypical easements or encumbrances were noted at the property during the appraiser's inspection.
H35: ZONING
H36: Designation | I36: I-1
H37: Description | I37: Industrial-1 (Light Industrial)
H38: Zoning Intent | I38: The purpose of the Industrial‐1 District is to provide a general commercial and limited industrial district designed to provide for a variety of compatible business, warehouse, wholesale, offices and very limited industrial uses. Special uses are permitted in an Industrial‐1 District, subject to the issuance of a Special Use Permit from the Board of Adjustment. Temporary uses are permitted in the Industrial‐1 District, subject to the issuance of a Temporary Use Permit from the Director of Community and Economic Development.
H39: Compliance | I39: The subject is a legal confirming use in the I-1 zoning designation.
H40: ZONING REQUIREMENTS
H41: Min. Lot Size: | I41: 1 Acre
H42: Min. Lot Width: | I42: 100 Feet
H43: Setbacks:
H44: Front | I44: 25 Feet
H45: Side | I45: 15 feet on one side and five 5 feet on the other side; 0 foot setbacks may be approved for fireproof structures.
H46: Rear | I46: 15 Feet
H47: Maximum Height: | I47: 60 Feet

Sheet Improvements
B2: =IF(OR(pdGenPropUse2="",pdGenPropUse2=0),"GENERAL DESCRIPTION OVERVIEW", "GENERAL DESCRIPTION OVERVIEW - "&UPPER(pdGenPropUse))
B3: Address | C3: ='Property Info'!B16
C4: ='Property Info'!B17
B5: Property Description | C5: =FE!U100
B6: Year Built | C6: ='Property Info'!B8
B7: Year Renovated | C7: =FE!U116
B8: Number of Buildings | C8: =FE!U120
B9: Number of Stories | C9: 1
B10: Total Number of Units | C10: =FE!U126
B11: Building Construction Class | C11: C/S
B12: Net Rentable Area | C12: =FE!U124
B13: Gross Leasable Area | C13: =FE!U122
B14: + Clubhouse | C14: =pdBldgAreaClubhouse
B15: + Others(s) | C15: =pdBldgAreaOther
B16: Mezzanine Area | C16: Small structural mezzanine located atop a temporary structure in the warehouse. Not included in the total GBA, considered an amenity of the property.
B17: Building Footprint | C17: ='Property Info'!B5
B18: Bay Depth | C18: =pdBayDepth
B19: LEED Ratio | C19: =pdLEEDRating
B20: Floor-Area Ratio | C20: =pdFAR
B21: Elevator(s) | C21: None
B22: Ceiling Heights | C22: 14'-23' (average 18')
B23: Utility Metering | C23: Master metered
B24: Density (Units/Acre) | C24: =C10/'Site Information'!C11
B25: Coverage Ratio | C25: =C17/'Site Information'!C11
B26: Land-to-Building Ratio | C26: ='Site Information'!C11/Improvements!C13
B27: Ingress/Egress | C27: Typical pedestrian entrances and loading doors along building perimeter.
B28: Percentage Office Build-Out | C28: ='Property Info'!B14
B29: Clear Height | C29: 12'-20'
B30: Power | C30: Assumed adequate for industrial use.
B31: Loading Doors
B32: Dock High | C32: 3
B33: Roll-Up | C33: 2
B34: Rail Access | C34: None
B35: Storage Yard | C35: Fenced storage yard located on the northwestern portion of the property.
B36: Truck Court | C36: Truck loading/unloading along the west and northeast building elevations.
B37: Parking
B38: Surface Parking Spaces | C38: 71
B39: Other | C39: 0
B40: Garages | C40: 0
B41: Total Parking Spaces | C41: =SUM(C38:C40)
B42: Parking Ratio (Spaces/1,000 SF GBA) | C42: =(C41/C13)*1000
B43: ADA Compliance | C43: =pdADA
B45: CONSTRUCTION DETAIL
B47: General Layout | C47: Primary pedestrian entrance located along the east building elevation, leading to a service window in the warehouse. Access to the office is available from the warehouse space. Office is located in the eastern portion of the building and is demised into a reception area, multiple private offices, conference room, administrative areas, and storage closets. Separate men's and woman's restrooms are located in the office. The warehouse is demised into a large open warehouse space, multiple storage rooms, break area, restrooms, work stations, an indoor loading dock, and several staging/shipping areas.
B48: Foundation | C48: Concrete slab on-grade under load-bearing structure
B49: Construction | C49: Masonry block, steel-frame
B50: Floor Structure | C50: Concrete slab
B51: Exterior Walls | C51: Insulated steel, masonry block
B52: Roof Type | C52: Structural steel
B53: Roof Cover | C53: Rubber membrane
B54: Windows | C54: Metal, double pane
B55: Balcony/Patios: | C55: None
B57: INTERIOR DETAIL
B59: Interior Walls | C59: Office: Painted drywall/Warehouse: Painted masonry block, exposed insulation, finished drywall.
B60: Ceilings | C60: Office: Acoustical tile/Warehouse: Exposed insulation, acoustical tile.
B61: Floor Coverings | C61: Office: Commercial-grade carpet, tile/Warehouse: Unfinished concrete.
B62: Doors | C62: Exterior: Insulated steel, Interior: Wood, composite.
B63: Lighting | C63: Office: Recessed fluorescent fixtures/Warehouse: Mounted LED and fluorescent fixtures.
B64: Ceiling Heights | C64: Office: 10'/Warehouse: 14'-23'
B65: Restrooms | C65: Separate men's and women's restrooms throughout.
B66: Kitchen Finish | C66: Manual fill.
B67: Bathroom Finish | C67: Manual fill.
B68: Amenities (Unit) | C68: Small structural mezzanine above temporary structure in warehouse (not part of GBA)
B70: MECHANICAL DETAIL
B71: Heating | C71: Multiple roof-mounted heating/cooling units serving office and warehouse spaces.
B72: Cooling | C72: Roof-mounted HVAC in office and warehouse
B73: Plumbing | C73: Assumed to code and adequate for light industrial use.
B74: Electrical | C74: =C73
B75: Fire Protection | C75: Wet sprinklers installed throughout.
B77: SITE IMPROVEMENTS
B78: Parking Type | C78: Surface
B79: Landscaping | C79: Perimeter grass and trees
B80: Signage | C80: Elevated building signage
B81: Fencing | C81: Perimeter fencing around storage yard area on northeastern portion of the property.
B82: Other | C82: Manual fill.
B83: Amenities (Project) | C83: Manual fill.
B85: RENOVATION/DEFERRED MAINTENANCE
B86: Recent Renovations or Replacements | C86: None reported
B87: Deferred Maintenance | C87: None reported. General maintenance items only.
B88: Cost to Cure | C88: =pdCosttoCure
B91: SUMMARY
B92: Building Condition | C92: =FE!U129
C93: We did not inspect the roof of the building(s) nor make a detailed inspection of the mechanical systems. We are not qualified to render an opinion as to the adequacy or condition of these components. Interested parties are urged to retain an expert in this field if detailed information is needed about the adequacy and condition of mechanical systems.
B94: Building Quality | C94: =FE!U130
B95: Design and Functionality | C95: =FE!U131
B96: Actual Age | C96: =2022-'Property Info'!B8
B97: Expected Economic Life | C97: 40
B98: Effective Age | C98: ='Cost Approach'!C40
B99: Remaining Economic Life | C99: =C97-C98

Sheet H&BU
C1: NOTE: Most of the below text is standard boilerplate and should remain the same. Read through and change only the descriptions as they pertain to your property.
B3: AS IF VACANT
B4: Legally | C4: Legal restrictions include deed restrictions, CC&R’s, lease encumbrances, zoning requirements, building codes, historic district controls and environmental regulations, and were previously analyzed to determine legally permitted uses. Legally, the subject is zoned I-1 (Light Industrial). The purpose of the Industrial‐1 District is to provide a general commercial and limited industrial district designed to provide for a variety of compatible business, warehouse, wholesale, offices and very limited industrial uses. Special uses are permitted in an Industrial‐1 District, subject to the issuance of a Special Use Permit from the Board of Adjustment. Temporary uses are permitted in the Industrial‐1 District, subject to the issuance of a Temporary Use Permit from the Director of Community and Economic Development. Allowable uses include but are not limited to storage, distribution, wholesale, office/flex, warehousing, maintenance, and light manufacturing.
B5: Physically | C5: Size, shape, topography, soil condition, availability of utilities, transportation access, surrounding uses, and locational characteristics were previously analyzed to determine which legal land uses are physically possible and which are best to conform to the physical and locational aspects of the site and its setting with respect to the neighborhood and community. Overall, the physical site attributes result in adequate utility, and the property could be developed with a variety of legally-conforming uses. Given the surrounding uses and location, the site is best suited for light industrial use.
B6: Financially | C6: Financial feasibility is determined by the relationship of supply and demand for the legally probable land uses versus the cost to create them. The market analysis section reveals that industrial uses in the subject's market are generally stabilized. Ongoing industrial development during the period in question throughout the market area serve as direct evidence that new industrial development was financially feasible at this time. Comparisons of rental rates, operating expenses and construction costs indicate the subject property would have been capable of providing an adequate return on investment to warrant new industrial development in the market. This assertion is supported by the fact that the property has the potential to generate rental income as shown in the income approach. Therefore, industrial use is considered financially feasible.
B7: Maximally | C7: The final test of highest and best use of the site as vacant is that the use be maximally productive, yielding the highest return to the land. In order to determine the maximally productive use, a comparison of rental rates, occupancy, operating expenses, and rates of return for the financially feasible uses have been made. Based on this analysis, light industrial use renders the highest residual land value; therefore, light industrial development on the subject's site is the maximally productive use of the subject as vacant.
B11: AS IMPROVED
B12: Legally | C12: The subject is a legal conforming use in the I-1 zoning district. No other known legal encumbrances exists that limit use or function on the improved property.
B13: Physically | C13: The subject is currently improved with a 33,950 square foot industrial building, located on a 2.49-acre site that conforms to its surrounding uses. Continued used of the improvements for industrial use is physically possible.
B14: Financially | C14: Financial feasibility as an income-producing investment is based on the amount of rental income it can generate net of the required operating expenses. If the resulting net operating income motivates continued operation, then the land is being put to a productive and financially feasible use. The subject is capable of producing positive net cash flow to an investor. The existing improvements provide contributory value to the site, and there is no alternate use that would result in a greater value. Therefore, utilization of the existing improvements is financially feasible.
B15: Maximally | C15: The maximally productive use should conform to neighborhood trends and be consistent with existing nearby land uses. The single use that produces the greatest return on investment and usually the highest price and value is typically the highest and best use. As shown in the applicable valuation sections, properties like the subject have been acquired and continue to be used for industrial use. None of the comparable properties were acquired for conversion to an alternative use. This provides evidence suggesting that the current industrial use is maximally productive.

Sheet Final Value
C2: VALUE INDICATIONS
C3: As Is - Land Value Only
C4: Sales Comparison Approach | D4: ='Land Sales'!C66 | E4: =D4/'Property Info'!B11 | F4: Per Square Foot (LA)
C5: Value Conclusion - As Is | D5: =D4 | E5: =E4 | F5: =F4
C6: As Is - Retrospective Market Value - Fee Simple Estate
C7: Cost Approach | D7: Not Developed
C8: Sales Comparison Approach | D8: ='Basic Sales Grid'!D46 | E8: =D8/'Property Info'!B4 | F8: =FE!B14
C9: Income Capitalization Approach
C10: Direct Capitalization | D10: ='Income Approach'!C65 | E10: =D10/'Property Info'!B6 | F10: =F8
C11: Approach Reliance | D11: =IF(FE!B14="GBA",'Final Value'!C8,'Final Value'!C9)
C12: Value Conclusion | D12: =D10 | E12: =D12/'Property Info'!B4 | F12: =F8
C13: As Is
C14: Sales Comparison Approach | D14: ='Basic Sales Grid'!D46 | E14: =D14/'Property Info'!B4 | F14: Per Square Foot (GBA)
C15: Income Capitalization Approach
C16: Direct Capitalization | D16: 1445000 | E16: =D16/3112 | F16: =F14
C17: Approach Reliance | D17: Sales Comparison Approach
C18: ="Value Conclusion - "&PROPER(bbValueConditionScen1)&"" | D18: =D14 | E18: =E14 | F18: =F14
C19: Exposure Time | D19: 12 months
C20: Marketing Time | D20: 12 months
G21: MARKET VALUE CONCLUSION
G22: Appraisal Premise | H22: Interest Appraised | I22: Date of Value | J22: Value Conclusion
G23: Retrospective Market Value | H23: Fee Simple | I23: ='Property Info'!B26 | J23: =D12
G26: 6 MONTH LIQUIDATION VALUE CONCLUSION
G27: Appraisal Premise | H27: Interest Appraised | I27: Date of Value | J27: Value Conclusion
G28: =bbValueNameScen1 | H28: Fee Simple | I28: 43132 | J28: 325000
G30: HYPOTHETICAL MARKET VALUE CONCLUSION (UNDERLYING LAND ONLY)
G31: Appraisal Premise | H31: Interest Appraised | I31: Date of Value | J31: Value Conclusion
G32: As If Vacant | H32: Fee Simple | I32: 43132 | J32: 200000
G34: PROSPECTIVE MARKET VALUE CONCLUSION
G35: Appraisal Premise | H35: Interest Appraised | I35: Date of Value | J35: Value Conclusion
G36: Upon Completion | H36: Fee Simple | I36: 43830 | J36: =D12

Sheet Land Sales
B1: NOTES:
B2: Change Highlighted fields only
B3: Change highlighted areas to WHITE when complete
B4: Check all cells for accuracy after completing
B5: Remember to spell check every worksheet as you go.
B7: COMPARABLE SALE ADJUSTMENT GRID
C8: Subject | D8: Sale 1 | F8: Sale 2 | H8: Sale 3 | J8: Sale 4 | L8: Sale 5
B9: Address | C9: ='Property Info'!B16 | E9: 3600 Chambers Road | G9: TBD - E 96th Avenue | I9: 2021 E 68th Avenue | K9: 6100 E 48th Avenue | L9: 10480-10555 West 63rd Place
B10: City, State | C10: ='Property Info'!B17 | E10: Aurora, CO | G10: Commerce City, CO | I10: Denver, CO | K10: Denver, CO | L10: Arvada, CO
B11: Account/Parcel Number | C11: ='Property Info'!B1 | E11: 1821-29-2-18-001 | G11: 1721-21-1-03-002 | I11: 1825-023-04-013 | K11: 1202-00-098-000 | L11: 39-091-07-003
B12: Property Type | C12: Industrial Land | E12: Industrial Land | G12: Industrial Land | I12: Industrial Land | K12: Industrial Land | L12: Commercial Land
B13: Sale Date | C13: N/A | E13: 43998 | G13: 43969 | I13: 43766 | K13: 43747 | L13: Under Contract
B14: Sale Price | C14: N/A | E14: 1800000 | G14: 1100000 | I14: 1350000 | K14: 795000 | L14: TBD
B15: Listing Price | C15: N/A | E15: Not Reported | G15: 1224040 | I15: 1600000 | K15: Not Reported | L15: 500000
B16: Days On Market | C16: N/A | E16: Not Reported | G16: 1117 | I16: 259 | K16: Not Reported | L16: 725
B17: Data Source | C17: Assessor, appraiser measurements | E17: Costar, Assessor Data, Deed, Troy DeVos (Buyer Representative) | G17: CoStar, Assessor Data, Listing Broker (Phil Foster & Co.) | I17: CoStar, Assessor Data, Listing Broker (Mark Goodman/Goodman Commercial) | K17: CoStar, Denver Assessor, Deed, Loan | L17: CoStar, Assessor, Listing
B18: Grantor | C18: TBD | E18: Josef Reith | G18: Josef Reith | I18: Josef Reith | K18: Terry & Nikki LLC | L18: 4950
B19: Grantee | C19: TBD | E19: AGG Real Estate LLC | G19: AGG Real Estate LLC | I19: AGG Real Estate LLC | K19: Dilligaff Inc | L19: 4950
B20: Site Size (SF) | C20: ='Property Info'!B11 | E20: 175405 | G20: 122404 | I20: 95912 | K20: 91793 | L20: 47916
B21: Zoning | C21: ='Property Info'!B29 | E21: B-3 (Business/Commercial) | G21: PUD-I (Industrial) | I21: I-2 (General Industrial) | K21: I-B (General Industrial) | L21: B-2
B22: Comments | C22: Industrial land | E22: Commercial/industrial land, purchased for development. | G22: Industrial parcel purchased for development. | I22: Industrial parcel purchased for development. | K22: Industrial parcel purchased for development. | L22: Commercial lot purchased for re-development. Formerly a mini-golf center.
B23: Unadjusted Price Per SF | E23: =E14/E20 | G23: =G14/G20 | I23: =I14/I20 | K23: =K14/K20 | M23: =L15/L20
B24: Quantified Adjustments
B25: Property Rights Conveyed | C25: Fee Simple | D25: Fee Simple | E25: 0 | F25: Fee Simple | G25: 0 | H25: Fee Simple | I25: 0 | J25: Fee Simple | K25: 0 | L25: Fee Simple
B26: Property Rights Conveyed Adjusted | E26: =IF(LEFT(CELL("format",E25),1)="P",E23*(1+E25),IF(LEFT(CELL("format",E25),1)="C",E23+E25)) | G26: =IF(LEFT(CELL("format",G25),1)="P",G23*(1+G25),IF(LEFT(CELL("format",G25),1)="C",G23+G25)) | I26: =IF(LEFT(CELL("format",I25),1)="P",I23*(1+I25),IF(LEFT(CELL("format",I25),1)="C",I23+I25)) | K26: =IF(LEFT(CELL("format",K25),1)="P",K23*(1+K25),IF(LEFT(CELL("format",K25),1)="C",K23+K25)) | M26: =IF(LEFT(CELL("format",M25),1)="P",M23*(1+M25),IF(LEFT(CELL("format",M25),1)="C",M23+M25))
B27: Financing | C27: N/A | D27: Market-Based | E27: 0 | F27: Market-Based | G27: 0 | H27: Market-Based | I27: 0 | J27: Market-Based | K27: 0 | L27: Market-Based | M27: 0
B28: Financing Adjusted | E28: =IF(LEFT(CELL("format",E27),1)="P",E26*(1+E27),IF(LEFT(CELL("format",E27),1)="C",E26+E27)) | G28: =IF(LEFT(CELL("format",G27),1)="P",G26*(1+G27),IF(LEFT(CELL("format",G27),1)="C",G26+G27)) | I28: =IF(LEFT(CELL("format",I27),1)="P",I26*(1+I27),IF(LEFT(CELL("format",I27),1)="C",I26+I27)) | K28: =IF(LEFT(CELL("format",K27),1)="P",K26*(1+K27),IF(LEFT(CELL("format",K27),1)="C",K26+K27)) | M28: =IF(LEFT(CELL("format",M27),1)="P",M26*(1+M27),IF(LEFT(CELL("format",M27),1)="C",M26+M27)) | R28: =0.25*J20
B29: Terms/Conditions of Sale | C29: N/A | D29: None | E29: 0 | F29: None | G29: 0 | H29: None | I29: 0 | J29: None | K29: 0 | L29: None | M29: 0
B30: Terms/Conditions of Sale Adjusted | E30: =IF(LEFT(CELL("format",E29),1)="P",E28*(1+E29),IF(LEFT(CELL("format",E29),1)="C",E28+E29)) | G30: =IF(LEFT(CELL("format",G29),1)="P",G28*(1+G29),IF(LEFT(CELL("format",G29),1)="C",G28+G29)) | I30: =IF(LEFT(CELL("format",I29),1)="P",I28*(1+I29),IF(LEFT(CELL("format",I29),1)="C",I28+I29)) | K30: =IF(LEFT(CELL("format",K29),1)="P",K28*(1+K29),IF(LEFT(CELL("format",K29),1)="C",K28+K29)) | M30: =IF(LEFT(CELL("format",M29),1)="P",M28*(1+M29),IF(LEFT(CELL("format",M29),1)="C",M28+M29))
B31: Expenditures After Sale | C31: N/A | D31: None | E31: 0 | F31: None | G31: 0 | H31: None | I31: 0 | J31: None | K31: 0 | L31: None | M31: 0
B32: Expenditures After Sale Adjusted | E32: =IF(LEFT(CELL("format",E31),1)="P",E30*(1+E31),IF(LEFT(CELL("format",E31),1)="C",E30+E31)) | G32: =IF(LEFT(CELL("format",G31),1)="P",G30*(1+G31),IF(LEFT(CELL("format",G31),1)="C",G30+G31)) | I32: =IF(LEFT(CELL("format",I31),1)="P",I30*(1+I31),IF(LEFT(CELL("format",I31),1)="C",I30+I31)) | K32: =IF(LEFT(CELL("format",K31),1)="P",K30*(1+K31),IF(LEFT(CELL("format",K31),1)="C",K30+K31)) | M32: =IF(LEFT(CELL("format",M31),1)="P",M30*(1+M31),IF(LEFT(CELL("format",M31),1)="C",M30+M31))
B33: Market Conditions | C33: N/A | D33: =D13 | E33: 0 | F33: =F13 | G33: 0 | H33: =H13 | I33: 0 | J33: =J13 | K33: 0 | L33: TBD | M33: 0
B34: Market Conditions Adjusted | E34: =IF(LEFT(CELL("format",E33),1)="P",E32*(1+E33),IF(LEFT(CELL("format",E33),1)="C",E32+E33)) | G34: =IF(LEFT(CELL("format",G33),1)="P",G32*(1+G33),IF(LEFT(CELL("format",G33),1)="C",G32+G33)) | I34: =IF(LEFT(CELL("format",I33),1)="P",I32*(1+I33),IF(LEFT(CELL("format",I33),1)="C",I32+I33)) | K34: =IF(LEFT(CELL("format",K33),1)="P",K32*(1+K33),IF(LEFT(CELL("format",K33),1)="C",K32+K33)) | M34: =IF(LEFT(CELL("format",M33),1)="P",M32*(1+M33),IF(LEFT(CELL("format",M33),1)="C",M32+M33))
B35: Total Quantified Adjustment | E35: =IFERROR(TEXT(E34-E23,"$#,##0.00")&CHAR(10)&" or "&CHAR(10)&TEXT((E34-E23)/E23,"0.00%"),0) | G35: =IFERROR(TEXT(G34-G23,"$#,##0.00")&CHAR(10)&" or "&CHAR(10)&TEXT((G34-G23)/G23,"0.00%"),0) | I35: =IFERROR(TEXT(I34-I23,"$#,##0.00")&CHAR(10)&" or "&CHAR(10)&TEXT((I34-I23)/I23,"0.00%"),0) | K35: =IFERROR(TEXT(K34-K23,"$#,##0.00")&CHAR(10)&" or "&CHAR(10)&TEXT((K34-K23)/K23,"0.00%"),0) | M35: =IFERROR(TEXT(M34-M23,"$#,##0.00")&CHAR(10)&" or "&CHAR(10)&TEXT((M34-M23)/M23,"0.00%"),0)
B36: Quantitatively Adjusted Price | E36: =E34 | G36: =G34 | I36: =I34 | K36: =K34 | M36: =M34
B37: Location | C37: ='Basic Sales Grid'!D28 | D37: Average | E37: 0 | F37: Average | G37: 0 | H37: Average | I37: 0 | J37: Fair | K37: 0.1 | L37: Below-Average | M37: 0.05
B38: Distance from Subject | C38: N/A | D38: 3 miles | F38: 3 miles | H38: 3 miles | J38: 1/4 mile | L38: Adjacent
B39: Surrounding Land Uses | C39: Retail, residential, developable land | D39: Retail, residential | F39: Retail, residential | H39: Retail, residential | J39: Retail, office, residential | L39: Retail, residential
B40: Quality/Condition of Surrounding Area | C40: Average to New | D40: Average to New | F40: Average to New | H40: Average to New | J40: Average to Very Good | L40: Average to Very Good
B41: Access to Commercial Services/Amenities | C41: Good | D41: Good | F41: Good | H41: Good | J41: Good | L41: Good
B42: Visibility/Access | C42: Average- access and visibility from two secondary thoroughfares. | D42: Above-Average: Primary thoroughfare exposure and access. Adjacent to 7-Eleven, Starbucks developments. | F42: Above-Average: Primary thoroughfare exposure and access. Adjacent to 7-Eleven, Starbucks developments. | H42: Above-Average: Primary thoroughfare exposure and access. Adjacent to 7-Eleven, Starbucks developments. | J42: Good - located along a primary thoroughfare | L42: Good - primary thoroughfare access/exposure
B43: Description | C43: Developing residential/retail area. Commercial thoroughfare exposure. Adjacent to anchored retail center. | D43: Primary thoroughfare exposure. Located in an area of developing retail/residential. Good commercial traffic. | F43: Primary thoroughfare exposure. Located in an area of developing retail/residential. Good commercial traffic. | H43: Primary thoroughfare exposure. Located in an area of developing retail/residential. Good commercial traffic. | J43: Visibility and access from W 120th Ave. (regional arterial) near anchored retail center and dene residential development. | L43: Located in an established residential/retail area of Arvada. Lower med. household incomes.
B44: =B20 | C44: =C20 | D44: =D20 | E44: 0.1 | F44: =F20 | G44: 0 | H44: =H20 | I44: 0 | J44: =J20 | K44: 0 | L44: =L20 | M44: -0.05
B45: Zoning | C45: =C21 | D45: =D21 | E45: 0 | F45: =F21 | G45: 0.05 | H45: =H21 | I45: -0.1 | J45: =J21 | K45: -0.05 | L45: B-2 (General Business) | M45: 0
B46: Utilities / Infrastructure | C46: Average | D46: Average | E46: 0 | F46: Average | G46: 0 | H46: Average | I46: 0 | J46: Average | K46: 0 | L46: Average | M46: 0
B47: Water/Sewer | C47: Available - Municipal Services | D47: Available - Municipal Services | F47: Available - Municipal Services | H47: Available - Municipal Services | J47: Available - Municipal Services | L47: Available - Municipal Services
B48: Electricity/Gas | C48: Available - Xcel Energy | D48: Available - Xcel Energy | F48: Available - Xcel Energy | H48: Available - Xcel Energy | J48: Available - Xcel Energy | L48: Available - Xcel Energy
B49: Other | C49: All available | D49: Historical Design | F49: Historical Design | H49: Historical Design | J49: Historical Design | L49: Historical Design
B50: Site Utility | C50: Average | D50: Average | E50: 0 | F50: Average | G50: 0 | H50: Average | I50: 0 | J50: Average | K50: 0 | L50: Average | M50: 0
B51: Site Shape | C51: Rectangular | D51: Rectangular | F51: Rectangular | H51: Rectangular | J51: Rectangular | L51: Generally rectangular
B52: Topography | C52: Generally Level | D52: Generally Level | F52: Generally Level | H52: Generally Level | J52: Generally Level | L52: Generally level
B53: Easement/Encroachments/Obstructions | C53: None known | D53: None known | F53: None known | H53: None known | J53: None known | L53: None known
B54: Other | C54: None | D54: None | F54: None | H54: None | J54: None | L54: None
B55: Total Non Quantified Adj. | E55: =SUM(E37,E44,E45,E46,E50) | G55: =SUM(G37,G44,G45,G46,G50) | I55: =SUM(I37,I44,I45,I46,I50) | K55: =SUM(K37,K44,K45,K46,K50) | M55: =SUM(M37,M44,M45,M46,M50)
B56: Indication for Subject: | E56: =IF(LEFT(CELL("format",E55),1)="P",E36*(1+E55),IF(LEFT(CELL("format",E55),1)="C",E36+E55)) | G56: =IF(LEFT(CELL("format",G55),1)="P",G36*(1+G55),IF(LEFT(CELL("format",G55),1)="C",G36+G55)) | I56: =IF(LEFT(CELL("format",I55),1)="P",I36*(1+I55),IF(LEFT(CELL("format",I55),1)="C",I36+I55)) | K56: =IF(LEFT(CELL("format",K55),1)="P",K36*(1+K55),IF(LEFT(CELL("format",K55),1)="C",K36+K55)) | M56: =IF(LEFT(CELL("format",M55),1)="P",M36*(1+M55),IF(LEFT(CELL("format",M55),1)="C",M36+M55))
B59: VALUE CONCLUSION - UNDERLYING LAND AREA
B60: Indicated Value per SF | C60: 10
B61: Land Area (SF) | C61: =C44
B62: =IF(C63=0,"HIDE THIS ROW IF NO DEFERRED MAINTENANCE", "Indicated Value") | C62: =C60*C61
B63: Contract Price | C63: 0
B65: =IF(SUM(C63:C63)=0,"Indicated Value","Indicated Value - Adjusted") | C65: =C60*C61
B66: 5000 | C66: =ROUND((C65/B66),0)*B66
B67: Per SF | C67: =C66/C61

Sheet M&S Inputs
A1: MARSHALL AND SWIFT (MVS) COST INPUTS -- June 2024 Edition
B2: Field | C2: Value (Input) | D2: Unit | E2: MVS Reference / Notes | F2: Source
A3: STEP 1 -- BUILDING IDENTIFICATION
B4: MVS Section | C4: Section 14 | D4: -- | E4: Section 14: Garages, Industrials and Warehouses (June 2024 ed.). PRIOR EDITIONS used Section 18 for industrials; June 2024 renumbered. Section 18 in June 2024 = Schools. | F4: MVS Sec.99 p.3
B5: Occupancy Code | C5: Occ. 406 | D5: -- | E5: 406 = Storage Warehouses. Other codes: 401 Service Garages, 402 Auto Dealerships, 403 Car Wash, 405 Commercial Garages, 407 Mfg. Light, 408 Mfg. Heavy. | F5: MVS Sec.14 p.26
B6: Building Class | C6: C | D6: -- | E6: A = Fire resistive concrete. B = Masonry/steel. C = Combustible frame. D = Wood frame/metal. S = Pre-engineered metal building. | F6: MVS Sec.14
B7: Quality | C7: Average | D7: -- | E7: Quality tiers: Low Cost | Average | Good | Excellent. Select relative to class standard. | F7: MVS Sec.14 p.26
B8: City / Local Area (for LAM lookup) | C8: Colorado Statewide | D8: -- | E8: Pick city from dropdown → auto-fills Local Area Multiplier (C19). Adams County: use 'Colorado Statewide' or 'Denver'.
A9: STEP 2 -- BASE COST AND SPRINKLER COST (per SF)
B10: Building Area (SF) [auto from Property Info] | C10: ='Property Info'!B4 | D10: SF | E10: Auto-linked from Property Info sheet. Used to interpolate sprinkler cost from TABLE D.
B11: Selected: Section / Class / Quality | C11: =C4&" / Occ. "&C5&" / Class "&C6&" / "&C7 | D11: -- | E11: Concatenated from Step 1 selections above -- confirms your lookup inputs.
B13: >>> Base cost auto-calculated from occupancy / class / quality above <<<
B14: Base Cost per SF [-> Cost Approach D6] | C14: =IFERROR(IF(C5="Occ. 406",INDEX($C$42:$C$62,MATCH(C6&"~"&C7,$D$42:$D$62,0)),INDEX($C$116:$C$123,MATCH(C6&"~"&C7,$D$116:$D$123,0))),"") | D14: $/SF | E14: Enter value from TABLE A (Occ.406 Storage Warehouse). Example: Class D / Average = .50/SF. Class D / Good = .00/SF. | F14: MVS Sec.14 p.26 (Feb 2024) | H14: Sprinkler Quality
B15: Sprinkler Add-On per SF (Wet System) [-> D7] | C15: =IFERROR(INDEX($B$98:$E$105,MATCH(C10,$A$98:$A$105,1),MATCH(H15,$B$97:$E$97,0)),"") | D15: $/SF | E15: From TABLE D. Interpolate by building area and quality. Example: 40,000 SF / Low Cost = .04/SF. Enter 0 if no sprinklers. | F15: MVS Sec.14 p.37 (Feb 2024) | H15: Average
A17: STEP 3 -- MULTIPLIERS
B18: Current Cost Multiplier [-> D15] | C18: =IFERROR(INDEX($B$81:$F$81,MATCH("Class "&IF(C6="C-Mill","C",IF(C6="D-Pole","D",C6)),$B$78:$F$78,0)),"") | D18: multiplier | E18: From TABLE C. Section 14 (eff. Feb 2024), Jan 2025 update. EASTERN region (Colorado): A=1.02, B=1.04, C=1.03, D=1.01, S=1.03. | F18: MVS Sec.99 p.3 (Jan 2025)
B19: Local Area Multiplier [-> D16] | C19: =IFERROR(INDEX($B$86:$F$93,MATCH(C8,$A$86:$A$93,0),MATCH("Class "&IF(C6="C-Mill","C",IF(C6="D-Pole","D",C6)),$B$85:$F$85,0)),"") | D19: multiplier | E19: From TABLE C2 (Colorado cities). Statewide D=1.01. Denver=1.00, Boulder=0.97, Fort Collins=0.99, Greeley=0.99, Pueblo=0.95. | F19: MVS Sec.99 p.7 (Jan 2025)
B20: Area Multiplier (avg of 2 size factors) [-> D17] | C20: =(E20+E21)/2 | D20: Area Factor 1 -> | E20: 0.876 | F20: Look up your SF in the size-adjustment table (Sec.14 p.25). Average two bracketing entries.
D21: Area Factor 2 -> | E21: 0.87
B22: Story Height Multiplier [-> D18] | C22: =IF(G22="",1,IFERROR(VLOOKUP(G22,$A$127:$B$142,2,TRUE),1)) | D22: multiplier | E22: From TABLE B. Base = 14 ft. Common: 20ft=1.133, 18ft=1.086, 16ft=1.041, 14ft=1.000, 12ft=0.960, 10ft=0.921. Enter actual clear eave height. | F22: Avg Eave/Wall Ht (ft) → | G22: 40
A24: STEP 4 -- SITE IMPROVEMENT RATES
B25: Asphalt Paving per SF [-> D22] | C25: 3.1 | D25: $/SF | E25: Sec.66 p.1 (Dec 2023). Large areas >3,000 SF: 4-inch asphalt .92-.51/SF, avg .10/SF. | F25: MVS Sec.66 p.1 (Dec 2023)
B26: Concrete Paving per SF [-> D24] | C26: 5.51 | D26: $/SF | E26: Sec.66 p.1 (Dec 2023). Large areas: 6-inch concrete .66-.71/SF, avg .51/SF. | F26: MVS Sec.66 p.1 (Dec 2023)
B27: Parking Striping per Space [-> D23] | C27: 20 | D27: $/space | E27: Market-derived. No MVS table. Typical range -/space. Adjust for painted vs. thermoplastic. | F27: Market data
B28: Landscaping per SF (lot area) [-> D27] | C28: 5.5 | D28: $/SF lot | E28: Sec.66 landscaping or market estimate. Applied to landscaped lot area. Adjust for density of planting and irrigation. | F28: MVS Sec.66 / market
A30: STEP 5 -- COST ADJUSTMENTS
B31: Indirect Costs % [-> C30] | C31: 0.1 | D31: % of construction | E31: Financing, permits, professional fees, insurance during construction. Typical 8%-15%. MVS default ~10%. | F31: MVS / market
B32: Entrepreneurial Profit % [-> C32] | C32: 0.15 | D32: % of (constr+indirect) | E32: Developer expected return above cost. Typical 10%-20%. MVS default ~15%. Adjust for market conditions. | F32: MVS / market
A34: STEP 6 -- DEPRECIATION OVERRIDES (enter 0 if none)
B35: Curable Deferred Maintenance ($) [-> F38] | C35: 0 | D35: $ | E35: Dollar cost to cure deferred items (roof, HVAC, etc.). Enter positive number. 0 = no curable items. | F35: Inspection / market
B36: Functional Obsolescence % [-> C43] | C36: 0 | D36: % of RCN | E36: Loss from design deficiencies (excess bays, substandard ceiling height, etc.). 0 = none. | F36: Market analysis
B37: External Obsolescence % [-> C44] | C37: 0 | D37: % of RCN | E37: Loss from external factors (market, economic, locational). 0 = none. | F37: Market analysis
A39: MVS QUICK-REFERENCE TABLES -- DO NOT EDIT (sourced from MVS June 2024 edition)
A40: TABLE A -- Occ. 406: Storage Warehouses | Base Cost per SF | MVS Sec.14, p.26 (Feb 2024)
A41: Class | B41: Quality | C41: $/SF | D41: Key (auto)
A42: A | B42: Good | C42: 137 | D42: A~Good
A43: A | B43: Average | C43: 101 | D43: A~Average
A44: A | B44: Low Cost | C44: 79.5 | D44: A~Low Cost
A45: B | B45: Good | C45: 121 | D45: B~Good
A46: B | B46: Average | C46: 88 | D46: B~Average
A47: B | B47: Low Cost | C47: 69 | D47: B~Low Cost
A48: C | B48: Excellent | C48: 134 | D48: C~Excellent
A49: C | B49: Good | C49: 86.5 | D49: C~Good
A50: C | B50: Average | C50: 61 | D50: C~Average
A51: C | B51: Low Cost | C51: 43 | D51: C~Low Cost
A52: C-Mill | B52: Good | C52: 119 | D52: C-Mill~Good
A53: C-Mill | B53: Average | C53: 82 | D53: C-Mill~Average
... A62: S | B62: Low Cost | C62: 38.75 | D62: S~Low Cost
A64: TABLE B -- Story Height Multipliers | Base = 14 ft | MVS Sec.14, p.39 (Feb 2024)
A65: Ht (ft) | B65: Multiplier | D65: Ht (ft) | E65: Multiplier
A66: 8 | B66: 0.885 | D66: 20 | E66: 1.133
A67: 10 | B67: 0.921 | D67: 22 | E67: 1.181
A68: 12 | B68: 0.96 | D68: 24 | E68: 1.231
A69: 14 | B69: 1.000 (BASE) | D69: 26 | E69: 1.281
A70: 16 | B70: 1.041 | D70: 28 | E70: 1.331
A71: 18 | B71: 1.086 | D71: 30 | E71: 1.382
D72: 35 | E72: 1.515
D73: 40 | E73: 1.65
D74: 45 | E74: 1.788
D75: 50 | E75: 1.93
A77: TABLE C -- Current Cost Multipliers | Sec.14 (eff. Feb 2024), Jan 2025 update | MVS Sec.99, p.3
A78: Region | B78: Class A | C78: Class B | D78: Class C | E78: Class D | F78: Class S
A79: WESTERN | B79: 1.07 | C79: 1.04 | D79: 1.06 | E79: 1.05 | F79: 1.04
A80: CENTRAL | B80: 1 | C80: 0.99 | D80: 0.99 | E80: 0.99 | F80: 0.99
A81: EASTERN | B81: 1.02 | C81: 1.04 | D81: 1.03 | E81: 1.01 | F81: 1.03
A82: NOTE: Colorado = EASTERN region for current cost multiplier purposes.
A84: TABLE C2 -- Colorado Local Area Multipliers | Jan 2025 update | MVS Sec.99, p.7
A85: City / Area | B85: Class A | C85: Class B | D85: Class C | E85: Class D | F85: Class S
A86: Colorado Statewide | B86: 1 | C86: 1.02 | D86: 1.02 | E86: 1.01 | F86: 1.02
A87: Denver | B87: 1.01 | C87: 1 | D87: 1 | E87: 1 | F87: 1.03
A88: Boulder | B88: 0.98 | C88: 0.98 | D88: 0.98 | E88: 0.97 | F88: 0.99
A89: Colorado Springs | B89: 0.98 | C89: 0.99 | D89: 0.96 | E89: 0.98 | F89: 1
A90: Fort Collins | B90: 0.98 | C90: 1 | D90: 1.01 | E90: 0.99 | F90: 1.01
A91: Grand Junction | B91: 0.98 | C91: 0.99 | D91: 1 | E91: 1 | F91: 1.02
A92: Greeley | B92: 0.98 | C92: 1 | D92: 1.01 | E92: 0.99 | F92: 0.99
A93: Pueblo | B93: 0.95 | C93: 0.95 | D93: 0.95 | E93: 0.95 | F93: 0.95
A94: NOTE: Adams County -- use Colorado Statewide (1.01 for Class D) or Denver (1.00 for Class D). Confirm with county practice.
A96: TABLE D -- Wet Sprinkler System Add-On per SF | MVS Sec.14, p.37 (Feb 2024)
A97: Coverage SF | B97: Low Cost | C97: Average | D97: Good | E97: Excellent
A98: 5000 | B98: 4.17 | C98: 5.02 | D98: 6.05 | E98: 7.28
A99: 10000 | B99: 3.77 | C99: 4.52 | D99: 5.41 | E99: 6.48
A100: 20000 | B100: 3.37 | C100: 4.02 | D100: 4.78 | E100: 5.7
A101: 40000 | B101: 3.04 | C101: 3.6 | D101: 4.27 | E101: 5.06
A102: 60000 | B102: 2.87 | C102: 3.39 | D102: 3.99 | E102: 4.71
A103: 100000 | B103: 2.66 | C103: 3.13 | D103: 3.68 | E103: 4.32
A104: 150000 | B104: 2.49 | C104: 2.92 | D104: 3.43 | E104: 4.03
A105: 200000 | B105: 2.4 | C105: 2.81 | D105: 3.28 | E105: 3.84
A107: TABLE E -- Site Paving Costs per SF | MVS Sec.66, pp.1-2 (Dec 2023)
A108: Paving Type | B108: Low | C108: Average | D108: High | E108: Notes
A109: 4-inch Asphalt (Large >3,000 SF) | B109: 2.92 | C109: 3.1 | D109: 3.51 | E109: Sec.66 p.1
A110: 6-inch Concrete (Large >3,000 SF) | B110: 4.66 | C110: 5.51 | D110: 7.71 | E110: Sec.66 p.1
A111: 2-inch Asphalt on 2-inch base (Small) | B111: 2.87 | C111: 3.56 | D111: 4.24 | E111: Sec.66 p.2
A112: 4-inch Concrete unreinforced (Small) | B112: 6.42 | C112: 8 | D112: 9.58 | E112: Sec.66 p.2
A114: TABLE F -- Occ. 407: Distribution Warehouses | Base Cost per SF | MVS Sec.14, p.23 (Feb 2024) | Space heaters configuration
A115: Class | B115: Quality | C115: $/SF | D115: Key
A116: A | B116: Good | C116: 123 | D116: A~Good
A117: A | B117: Average | C117: 108 | D117: A~Average
A118: B | B118: Good | C118: 103 | D118: B~Good
A119: B | B119: Average | C119: 70.5 | D119: B~Average
A120: C | B120: Excellent | C120: 92.5 | D120: C~Excellent
...

Sheet Cost Approach
A1: COST APPROACH | I1: NOTES
I2: Change Highlighted fields only
B3: COST APPROACH SUMMARY | I3: Change highlighted areas to WHITE when complete
B4: Replacement Cost New (RCN) | C4: Area (SF) | D4: $/SF | F4: Subtotal | G4: Total Cost | I4: Check all cells for accuracy after completing
B5: Building Improvements | I5: Remember to spell check every worksheet as you go.
B6: Base Cost | C6: ='Property Info'!B4 | D6: ='M&S Inputs'!C14 | F6: =C6*D6 | I6: LAND VALUE IS SET TO VALUE CONCLUDED IN THE LAND SALES WORKSHEET.
B7: Sprinklers | C7: =C6 | D7: ='M&S Inputs'!C15 | F7: =C7*D7 | I7: IF YOU ARE USING LAND VALUE FROM REALWARE, OVERWRITE THAT CELL WITH THE
B13: Subtotal | F13: =SUM(F6:F12) | I13: APPROPRIATE LAND VALUE.
B14: Multipliers
B15: Current Cost | D15: ='M&S Inputs'!C18
B16: Local Area | D16: ='M&S Inputs'!C19
B17: Area Multiplier | D17: ='M&S Inputs'!C20
B18: Story Height (Assumed 18' Average) | D18: ='M&S Inputs'!C22
B19: Product of Multipliers | F19: =ROUND(PRODUCT(D15:D18),3)
B20: Adjusted Base Building Cost | G20: =F19*F13
B21: Site Improvements (Component SF Based on Appraiser Measurement)
B22: Parking/Loading Areas (asphalt) | C22: 37800 | D22: ='M&S Inputs'!C25 | F22: =D22*C22
B23: Striping (Per Space) | C23: 71 | D23: ='M&S Inputs'!C27 | F23: =D23*C23
B24: Paving (concrete) | C24: =3564.94+334.9+942.42+495 | D24: ='M&S Inputs'!C26 | F24: =D24*C24
B25: Other1 | F25: =D25*C25
B26: Other2 | F26: =D26*C26
B27: Landscaping, Lighting, Other Site Improvements | C27: =27877.68+472.99 | D27: ='M&S Inputs'!C28 | F27: =D27*C27
B28: Total Site Improvements | G28: =SUM(F22:F27)
B29: Total Construction Costs | G29: =SUM(G20:G28)
B30: Plus Other Indirect Costs (% of Direct Costs) | C30: ='M&S Inputs'!C31 | G30: =G29*(C30)
B31: Subtotal Replacement Cost New (RCN) | G31: =SUM(G29:G30)
B32: Plus Entrepreneurial Profit (% of RCN) | C32: ='M&S Inputs'!C32 | G32: =G31*C32
B33: Total Replacement Cost New (RCN) | G33: =SUM(G31:G32)
B34: per square foot of gross building area | G34: =caRCN/10000
B36: Less Accrued Depreciation
B37: Physical
B38: Curable (Deferred Maintenance) | F38: ='M&S Inputs'!C35
B39: Incurable | U39: 251225
B40: Effective Age (Years) | C40: =Improvements!C98 | U40: 5000
B41: Economic Life | C41: =Improvements!C97 | U41: 138125
B42: Total Incurable Physical Depreciation | C42: =C40/C41 | F42: =G33*C42 | U42: 198000
B43: Functional Obsolescence | C43: ='M&S Inputs'!C36 | F43: =C43*caRCN | U43: =SUM(U39:U42)
B44: External Obsolescence | C44: ='M&S Inputs'!C37 | F44: =C44*caRCN
B45: Total | C45: =G45/caRCN | G45: =SUM(F38:F44)
B46: Depreciated Value of the Improvements | G46: =G33-G45
B47: per square foot of gross building area | G47: =caRCNDeprec/10000
B49: Plus Land Value | G49: ='Land Sales'!C65
B51: Indicated Value by Cost Approach | G51: =G46+G49
B52: 5000 | G52: =ROUND((G51/B52),0)*B52
B53: per square foot of gross building area | G53: =G52/C6
B55: MVS June 2024 Ed. | C55: ="Occ. 406 Storage Warehouse | "&'M&S Inputs'!C4&" | "&'M&S Inputs'!C5 | D55: ="Class: "&'M&S Inputs'!C6&" / "&'M&S Inputs'!C7
B56: Colorado -- EASTERN region | C56: ="CCM: "&TEXT('M&S Inputs'!C18,"0.000")&" | LAM: "&TEXT('M&S Inputs'!C19,"0.000") | D56: Sec.99 p.3 and p.7 (Jan 2025 update)
C57: ="Story Ht Mult: "&TEXT('M&S Inputs'!C22,"0.000")&" | Area Mult: "&TEXT('M&S Inputs'!C20,"0.000")
B66: COST APPROACH SUMMARY - MVS
B67: Replacement Cost New (RCN) | C67: Area (SF) | D67: $/SF | F67: Subtotal | G67: Total Cost
B68: Building Improvements
B69: Base Cost | C69: ='Property Info'!B4 | D69: 69 | F69: =C69*D69
B70: Sprinklers | C70: ='Property Info'!B4 | D70: 4.5 | F70: =D70*C70
B76: Subtotal | F76: =SUM(F69:F75)
B77: Multipliers
B78: Current Cost | D78: 1.01
B79: Local Area | D79: 0.96
B80: Area Multiplier | D80: 0.949
B81: Story Height | D81: 1
B82: Product of Multipliers | F82: =ROUND(PRODUCT(D78:D81),3)
B83: Adjusted Base Building Cost | G83: =F82*F76
B84: Site Improvements
B85: Paving (asphalt)
B86: Paving (concrete)
B87: Other1
B88: Other2
B89: Landscaping, Lighting, Other Site Improvements | C89: =C27 | D89: 4.5 | F89: =C89*D89
B90: Total Site Improvements | G90: =SUM(F85:F89)
B91: Total Direct Costs | G91: =SUM(G83:G90)
B92: Plus Other Indirect Costs (% of Direct Costs) | C92: 0.15 | G92: =G91*(C92)
B93: Subtotal Replacement Cost New (RCN) | G93: =SUM(G91:G92)
B94: Plus Entrepreneurial Profit (% of RCN) | C94: 0.15 | G94: =G93*C94
B95: Total Replacement Cost New (RCN) | G95: =SUM(G93:G94)
B96: per square foot of gross building area | G96: =G95/C70
B98: Less Accrued Depreciation
B99: Physical
B100: Curable (Deferred Maintenance) | F100: 0
B101: Incurable
B102: Effective Age (Years) | C102: 15
B103: Economic Life | C103: 45
B104: Total Incurable Physical Depreciation | C104: =C102/C103 | F104: =G95*C104
B105: Functional Obsolescence | C105: 0 | F105: =C105*caRCN
B106: External Obsolescence | C106: 0 | F106: =C106*caRCN
B107: Total | C107: =G107/caRCN | G107: =SUM(F100:F106)
B108: Depreciated Value of the Improvements | G108: =G95-G107
B109: per square foot of gross building area | G109: =caRCNDeprec/10000
B111: Plus Land Procurement Cost | G111: ='Land Sales'!C66
B113: Indicated Value by Cost Approach | G113: =G108+G111
B114: 5000 | G114: =ROUND((G113/B114),0)*B114
B115: per square foot of gross building area | G115: =G114/C69
B116: Source: Marshall Valuation Service | C116: Date: Feb. 2019
B117: Type: 407 - Industrial Warehouse | C117: Section: 18 | D117: Page: 13 | F117: Class: C | G117: Quality: Good
B119: INSURABLE VALUE
B120: Replacement Cost (Base Cost) | D120: =G29
B121: Plus: Indirect Costs | D121: 0
B122: Plus: Entrepreneurial Profit (Est. 5% of Replacement and Indirect Cost) | D122: =G32
B123: Replacement Cost (Base Cost + Indirect Costs + Profit | D123: =SUM(D120,D121,D122)
B124: Less: 5% of Replacement Costs for Excavations/Foundations | C124: =ROUND(-0.05*D123, 0)
B125: Less: Site Work not included in Excavations/Foundations | C125: 0
B126: Less: 5% of Replacement Costs for Architect's Fees | C126: =ROUND(-0.05*D123, 0)
...

Sheet Construction Costs
B2: Subject's Budgeted Construction Costs
B3: Item | C3: Cost | D3: Cost PSF
B4: Site Inspection, Architectural & Engineering | C4: 208225 | D4: =C4/'Property Info'!$B$4
B5: Government Fees & Permits | C5: 406500 | D5: =C5/'Property Info'!$B$4
B6: Site Improvements | C6: 733000 | D6: =C6/'Property Info'!$B$4
B7: Off-Site Construction | C7: 105000 | D7: =C7/'Property Info'!$B$4
B8: Vertical Improvements | C8: 2150000 | D8: =C8/'Property Info'!$B$4
B9: Contractor Overhead & Profit | C9: 375000 | D9: =C9/'Property Info'!$B$4
B10: Indirect Costs | D10: =C10/'Property Info'!$B$4
B11: Total | C11: =SUM(C4:C10) | D11: =C11/'Property Info'!$B$4
F12: Comparable Constrution Cots
F13: Comparable | G13: 1 | H13: 2 | I13: 3 | J13: 4
F14: Location | G14: Metro Denver | H14: Metro Denver | I14: Metro Denver | J14: Metro Denver
F15: YOC | G15: 2015 | H15: 2016 | I15: 2019 | J15: 2019
F16: Property Type | G16: Franchise Daycare | H16: Franchise Daycare | I16: Franchise Daycare | J16: Franchise Daycare
F17: Total Direct Cost | G17: 255.16 | H17: 325.13 | I17: 420.5 | J17: 344.08

Sheet Export030823
B1: Property Address | C1: Property City | D1: Account/Parcel | E1: Property Type | F1: Sale Date | G1: Sale Price | H1: Price ($/SF) | I1: Asking Price | J1: DOM | K1: Building SF | L1: Land Area SF | M1: Property Rights Conveyed | N1: Financing | O1: Terms/ Conditions of Sale | P1: Expenditures After Sale | Q1: Market Conditions | R1: Location | S1: Property Size (SF) | T1: YOC / Condition | U1: Quality | V1: Land-To-Building Ratio | W1: Tenancy / Occupancy | X1: Functional Utility | Y1: Total Net Adj. | Z1: Adjusted Price ($/SF)
A2: A | B2: ='Property Info'!B16 | C2: ='Property Info'!B17 | D2: ='Property Info'!B1 | E2: ='Property Info'!B15 | F2: N/A | G2: N/A | H2: N/A | I2: N/A | J2: N/A | K2: =FE!C14 | L2: ='Property Info'!B11 | M2: ='Property Info'!B24 | N2: N/A | O2: N/A | P2: N/A | Q2: N/A | R2: Average | S2: =K2 | T2: ='Property Info'!B10 | U2: Average | V2: =L2/K2 | W2: Average | X2: Average | Y2: N/A | Z2: N/A
A3: 1 | B3: 9670 Dallas St (Condo) | C3: Henderson | D3: 1721-15-3-03-001 | E3: Industrial | F3: 44742 | G3: 630000 | H3: 210 | I3: 525000 | J3: 289 | K3: 3000 | M3: 0 | N3: 0 | O3: 0 | P3: 0 | Q3: 0 | R3: 0.05 | S3: -0.05 | T3: 0 | U3: 0 | V3: 0 | W3: 0 | X3: 0 | Y3: =SUM(M3:X3) | Z3: =H3+(H3*Y3)
A4: 2 | B4: 9652 Hanover Ct W | C4: Henderson | D4: 1721-15-0-11-005 | E4: Industrial | F4: 44637 | G4: 4600000 | H4: 197.87 | K4: 23248 | L4: 73704 | M4: 0 | N4: 0 | O4: 0 | P4: 0 | Q4: 0 | R4: 0 | S4: 0 | T4: 0 | U4: -0.1 | V4: 0 | W4: 0 | X4: 0 | Y4: =SUM(M4:X4) | Z4: =H4+(H4*Y4)
A5: 3 | B5: 9690 Dallas St (Condo) | C5: Henderson | D5: 1721-15-3-03-013 | E5: Industrial | F5: 44631 | G5: 525000 | H5: 175 | K5: 3000 | L5: 93218 | M5: 0 | N5: 0 | O5: 0 | P5: 0 | Q5: 0 | R5: 0 | S5: -0.05 | T5: 0 | U5: -0.05 | V5: 0.05 | W5: 0.05 | X5: 0 | Y5: =SUM(M5:X5) | Z5: =H5+(H5*Y5)
A6: 4 | B6: 9900 Emporia St (Part of a 2 Property Sale) | C6: Commerce City | D6: 1721-15-4-04-003 | E6: Industrial | F6: 44537 | G6: 9728033 | H6: 640 | K6: 15200 | L6: 487436 | M6: 0 | N6: 0 | O6: 0 | P6: 0 | Q6: 0.05 | R6: 0 | S6: 0 | T6: 0 | U6: 0 | V6: 0.05 | W6: 0 | X6: 0 | Y6: =SUM(M6:X6) | Z6: =H6+(H6*Y6)
A7: 5 | B7: 10400 E 102nd Ave | C7: Commerce City | D7: 1721-15-1-02-013 | E7: Industrial | F7: 44517 | G7: 13000000 | H7: 739.6 | K7: 17577 | L7: 700880
B8: Average | H8: =AVERAGE(H3:H7) | Z8: =AVERAGE(Z3:Z7)
B9: Median | H9: =MEDIAN(H3:H7) | Z9: =MEDIAN(Z3:Z7)
B10: Standard Dev. | H10: =_xlfn.STDEV.P(H3:H6) | Z10: =_xlfn.STDEV.P(Z3:Z6)
R12: Comp | S12: % Size Diff. | V12: LTB
R13: 1 | S13: =(K3-$K$2)/$K$2 | V13: =L3/K3
R14: 2 | S14: =(K4-$K$2)/$K$2 | V14: =L4/K4
R15: 3 | S15: =(K5-$K$2)/$K$2 | V15: =L5/K5
R16: 4 | S16: =(K6-$K$2)/$K$2 | V16: =L6/K6
R17: 5 | S17: =(K7-$K$2)/$K$2 | V17: =L7/K7

Sheet Basic Sales Grid
C2: COMPARABLE SALE ADJUSTMENT GRID
D3: Subject | E3: Sale 1 | F3: Sale 2 | G3: Sale 3 | H3: Sale 4 | I3: Sale 5 | J3: Listing 1
C4: Address | D4: =Export030823!B2 | E4: =Export030823!B3 | F4: =Export030823!B4 | G4: =Export030823!B5 | H4: =Export030823!B6 | I4: =Export030823!B7 | J4: 3555 West 144th Avenue
C5: City, State | D5: =Export030823!C2 | E5: =Export030823!C3 | F5: =Export030823!C4 | G5: =Export030823!C5 | H5: =Export030823!C6 | I5: =Export030823!C7 | J5: Broomfield
C6: Parcel Number | D6: =Export030823!D2 | E6: =Export030823!D3 | F6: =Export030823!D4 | G6: =Export030823!D5 | H6: =Export030823!D6 | I6: =Export030823!D7 | J6: 1573-173-14-002
C7: Property Type | D7: =Export030823!E2 | E7: =Export030823!E3 | F7: =Export030823!E4 | G7: =Export030823!E5 | H7: =Export030823!E6 | I7: =Export030823!E7 | J7: ST Daycare Building
C8: Sale Date | D8: N/A | E8: =Export030823!F3 | F8: =Export030823!F4 | G8: =Export030823!F5 | H8: =Export030823!F6 | I8: =Export030823!F7 | J8: TBD (Active Listing)
C9: Sale Price | D9: N/A | E9: =Export030823!G3 | F9: =Export030823!G4 | G9: =Export030823!G5 | H9: =Export030823!G6 | I9: =Export030823!G7 | J9: N/A
C10: Listing Price | D10: N/A | E10: =Export030823!I3 | F10: =Export030823!I4 | G10: =Export030823!I5 | H10: =Export030823!I6 | I10: =Export030823!I7 | K10: 6769231
C11: Days On Market | D11: N/A | E11: =Export030823!J3 | F11: =Export030823!J4 | G11: =Export030823!J5 | H11: =Export030823!J6 | I11: =Export030823!J7 | J11: 73
C12: Data Source | D12: Inspection, Lease, Site Plans, Assessor | E12: CoStar, Assessor, Deed | F12: CoStar, Assessor, Deed | G12: CoStar, Assessor, Deed | H12: CoStar, Assessor, Deed | I12: CoStar, Assessor, Offering Memorandum | J12: CoStar, Assessor, Offering Memorandum
C13: Property Size (SF) | D13: =Export030823!K2 | E13: =Export030823!K3 | F13: =Export030823!K4 | G13: =Export030823!K5 | H13: =Export030823!K6 | I13: =Export030823!K7 | J13: 10511
C14: Site Size (SF) | D14: =Export030823!L2 | E14: =Export030823!L3 | F14: =Export030823!L4 | G14: =Export030823!L5 | H14: =Export030823!L6 | I14: =Export030823!L7 | J14: 67954
C15: Parking Spaces | D15: 41 | J15: 28
C16: Comments | D16: Single-tenant daycare facility 100% leased long-term to KinderCare on a guaranteed net agreement. | J16: Single-tenant daycare facility 100% leased long-term to Little Sunshine's Playhouse and Preschool, a national tenant.
C17: Unadjusted Price Per SF | E17: =E9/E13 | F17: =F9/F13 | G17: =G9/G13 | H17: =H9/H13 | I17: =I9/I13 | K17: =K10/J13
C18: Quantified Adjustments
C19: Sale Type | D19: =Export030823!M2 | E19: =Export030823!M3 | F19: =Export030823!M4 | G19: =Export030823!M5 | H19: =Export030823!M6 | I19: =Export030823!M7 | J19: Leased Fee
C20: Financing | D20: Market Based | E20: =Export030823!N3 | F20: =Export030823!N4 | G20: =Export030823!N5 | H20: =Export030823!N6 | I20: =Export030823!N7 | K20: 0
C21: Terms/Conditions of Sale | D21: None | E21: =Export030823!O3 | F21: =Export030823!O4 | G21: =Export030823!O5 | H21: =Export030823!O6 | I21: =Export030823!O7 | J21: Active Listing | K21: -0.05
C22: Expenditures After Sale | D22: None | E22: =Export030823!P3 | F22: =Export030823!P4 | G22: =Export030823!P5 | H22: =Export030823!P6 | I22: =Export030823!P7 | K22: 0
C23: Market Conditions | D23: N/A | E23: =Export030823!Q3 | F23: =Export030823!Q4 | G23: =Export030823!Q5 | H23: =Export030823!Q6 | I23: =Export030823!Q7 | K23: 0
C24: Market Conditions Adjusted | E24: =IF(LEFT(CELL("format",E23),1)="P",E17*(1+E23),IF(LEFT(CELL("format",E23),1)="C",E17+E23)) | F24: =IF(LEFT(CELL("format",F23),1)="P",F17*(1+F23),IF(LEFT(CELL("format",F23),1)="C",F17+F23)) | G24: =IF(LEFT(CELL("format",G23),1)="P",G17*(1+G23),IF(LEFT(CELL("format",G23),1)="C",G17+G23)) | H24: =IF(LEFT(CELL("format",H23),1)="P",H17*(1+H23),IF(LEFT(CELL("format",H23),1)="C",H17+H23)) | I24: =IF(LEFT(CELL("format",I23),1)="P",I17*(1+I23),IF(LEFT(CELL("format",I23),1)="C",I17+I23)) | K24: =IF(LEFT(CELL("format",K23),1)="P",K17*(1+K23),IF(LEFT(CELL("format",K23),1)="C",K17+K23))
C25: Total Quantified Adjustment | E25: =SUM(E19:E23) | F25: =SUM(F19:F23) | G25: =SUM(G19:G23) | H25: =SUM(H19:H23) | I25: =SUM(I19:I23) | K25: =IFERROR(TEXT(K24-K17,"$#,##0.00")&CHAR(10)&" or "&CHAR(10)&TEXT((K24-K17)/K17,"0.00%"),0)
C26: Quantitatively Adjusted Price | E26: =E17+(E17*E25) | F26: =F17+(F17*F25) | G26: =G17+(G17*G25) | H26: =H17+(H17*H25) | I26: =I17+(I17*I25) | K26: =K24
C27: Qualitative Adjustments | K27: =SUM(K19:K25)+1
C28: =Export030823!R1 | D28: =Export030823!R2 | E28: =Export030823!R3 | F28: =Export030823!R4 | G28: =Export030823!R5 | H28: =Export030823!R6 | I28: =Export030823!R7 | J28: Good | K28: 0
C29: =Export030823!S1 | D29: =Export030823!S2 | E29: =Export030823!S3 | F29: =Export030823!S4 | G29: =Export030823!S5 | H29: =Export030823!S6 | I29: =Export030823!S7 | J29: =J13 | K29: 0
C30: =Export030823!T1 | D30: =Export030823!T2 | E30: =Export030823!T3 | F30: =Export030823!T4 | G30: =Export030823!T5 | H30: =Export030823!T6 | I30: =Export030823!T7 | J30: 2019 / Very Good | K30: 0
C31: =Export030823!U1 | D31: =Export030823!U2 | E31: =Export030823!U3 | F31: =Export030823!U4 | G31: =Export030823!U5 | H31: =Export030823!U6 | I31: =Export030823!U7 | J31: Good | K31: 0
C32: =Export030823!V1 | D32: =Export030823!V2 | E32: =Export030823!V3 | F32: =Export030823!V4 | G32: =Export030823!V5 | H32: =Export030823!V6 | I32: =Export030823!V7 | J32: =ROUND((J15/J13)*1000,2)& ":1,000 SF" | K32: 0
C33: =Export030823!W1 | D33: =Export030823!W2 | E33: =Export030823!W3 | F33: =Export030823!W4 | G33: =Export030823!W5 | H33: =Export030823!W6 | I33: =Export030823!W7 | J33: Good | K33: 0
C34: =Export030823!X1 | D34: =Export030823!X2 | E34: =Export030823!X3 | F34: =Export030823!X4 | G34: =Export030823!X5 | H34: =Export030823!X6 | I34: =Export030823!X7 | J34: Good | K34: 0
C35: Total Non Quantified Adj. | E35: =SUM(E28,E29,E30,E31,E32,E33,E34) | F35: =SUM(F28,F29,F30,F31,F32,F33,F34) | G35: =SUM(G28,G29,G30,G31,G32,G33,G34) | H35: =SUM(H28,H29,H30,H31,H32,H33,H34) | I35: =SUM(I28,I29,I30,I31,I32,I33,I34) | K35: =SUM(K28,K29,K30,K31,K32,K33,K34)
C36: Indication for Subject: | E36: =E26+(E26*E35) | F36: =F26+(F26*F35) | G36: =G26+(G26*G35) | H36: =H26+(H26*H35) | I36: =I26+(I26*I35) | K36: =IF(LEFT(CELL("format",K35),1)="P",K26*(1+K35),IF(LEFT(CELL("format",K35),1)="C",K26+K35))
C39: SALES COMPARISON APPROACH VALUE CONCLUSION
C40: Indicated Value per SF | D40: 120
C41: Building Area (SF) | D41: ='Property Info'!B4
C42: =IF(D43=0,"HIDE THIS ROW IF NO DEFERRED MAINTENANCE", "Indicated Value") | D42: =D40*D41
C43: Contract Price | D43: 0
C44: =D42+D43
C45: =IF(SUM(D43:D43)=0,"Indicated Value","Indicated Value - Adjusted") | D45: =C44
C46: 5000 | D46: =ROUND((D45/C46),0)*C46
C47: Per SF | D47: =D46/D41
C51: Assessor's Assigned Value | D51: ='Property Info'!B20 | E51: =D51/D29
C52: Petition Value | D52: ='Property Info'!B21 | E52: ='Basic Sales Grid'!D52/'Basic Sales Grid'!D29 | O52: COMPARABLE SALE SEARCH
O53: SEARCH FOR COMPARABLE SALES
O54: Property Type Searched | P54: Industrial
O55: Search Radius | P55: 5-Miles
O56: SF Parameters | P56: 20,000 SF - 40,000 SF
O57: Property Rights Conveyed | P57: Fee Simple
O58: COMPARABLES UTILIZED
O59: Sales | P59: 4
O60: Confirmations | P60: All pertinent information verified.
R63: RANKING OF THE SUBJECT PROPERTY
R64: COMPARABLE | S64: VALUE PSF | T64: COMPARISON
R65: 4 | S65: =H36 | T65: Below
R66: 2 | S66: =F36 | T66: Below
R67: Subject | S67: 120
R68: 3 | S68: =G36 | T68: Above
R69: 1 | S69: =E36 | T69: Above
R70: 1 | S70: 69.87 | T70: Inferior

Sheet Detailed Sales Grid
C2: COMPARABLE SALE ADJUSTMENT GRID
D3: Subject
C4: Address | D4: 5668 North Beeler Street
C5: City, State | D5: Denver, CO
C6: Parcel Number | D6: 1103-40-003-000
C7: Property Type | D7: Daycare Building
C8: Sale Date | D8: N/A
C9: Sale Price | D9: 6555000
C10: Listing Price | D10: 6555000
C11: Days On Market | D11: N/A
C12: Data Source | D12: Assessor, Inspection, Buyer, Lease
C13: Property Size (SF) | D13: ='Property Info'!B4
C14: Site Size (SF) | D14: ='Property Info'!B11 | V14: COMPARABLE SALE ADJUSTMENT GRID
C15: Parking Spaces | D15: 26
C16: Comments | D16: Owner-user daycare facility | E16: Single-tenant daycare facility 100% leased long-term to Prestige Preschool Academy, a national tenant. | G16: Daycare Facility, leased to a franchise tenant at TOS. | I16: Daycare facility, leased to a local tenant at TOS. | K16: Daycare building, local franchise lease at TOS. | M16: Daycare building, local franchise lease at TOS. | O16: Daycare facility, leased to a franchise daycare service on a 15 year agreement. Two 5-year renewal options available.
C17: Unadjusted Price Per SF | D17: =D9/D13 | F17: =E9/E13 | H17: =G9/G13 | J17: =I9/I13 | L17: =K9/K13 | N17: =M9/M13 | P17: =O9/O13
C18: Quantified Adjustments
C19: Property Rights Conveyed | D19: Leased Fee | E19: Leased Fee | F19: 0 | G19: Leased Fee | H19: 0 | I19: Leased Fee | J19: 0 | K19: Leased Fee | L19: 0 | M19: Leased Fee | N19: 0 | O19: Leased Fee
C20: Property Rights Conveyed Adjusted | F20: =IF(LEFT(CELL("format",F19),1)="P",F17*(1+F19),IF(LEFT(CELL("format",F19),1)="C",F17+F19)) | H20: =IF(LEFT(CELL("format",H19),1)="P",H17*(1+H19),IF(LEFT(CELL("format",H19),1)="C",H17+H19)) | J20: =IF(LEFT(CELL("format",J19),1)="P",J17*(1+J19),IF(LEFT(CELL("format",J19),1)="C",J17+J19)) | L20: =IF(LEFT(CELL("format",L19),1)="P",L17*(1+L19),IF(LEFT(CELL("format",L19),1)="C",L17+L19)) | N20: =IF(LEFT(CELL("format",N19),1)="P",N17*(1+N19),IF(LEFT(CELL("format",N19),1)="C",N17+N19)) | P20: =IF(LEFT(CELL("format",P19),1)="P",P17*(1+P19),IF(LEFT(CELL("format",P19),1)="C",P17+P19))
C21: Financing | D21: N/A | E21: Market-Based | F21: 0 | G21: Market-Based | H21: 0 | I21: Market-Based | J21: 0 | K21: Market-Based | L21: 0 | M21: Market-Based | N21: 0 | O21: N/A | P21: 0
C22: Financing Adjusted | F22: =IF(LEFT(CELL("format",F21),1)="P",F20*(1+F21),IF(LEFT(CELL("format",F21),1)="C",F20+F21)) | H22: =IF(LEFT(CELL("format",H21),1)="P",H20*(1+H21),IF(LEFT(CELL("format",H21),1)="C",H20+H21)) | J22: =IF(LEFT(CELL("format",J21),1)="P",J20*(1+J21),IF(LEFT(CELL("format",J21),1)="C",J20+J21)) | L22: =IF(LEFT(CELL("format",L21),1)="P",L20*(1+L21),IF(LEFT(CELL("format",L21),1)="C",L20+L21)) | N22: =IF(LEFT(CELL("format",N21),1)="P",N20*(1+N21),IF(LEFT(CELL("format",N21),1)="C",N20+N21)) | P22: =IF(LEFT(CELL("format",P21),1)="P",P20*(1+P21),IF(LEFT(CELL("format",P21),1)="C",P20+P21))
C23: Terms/Conditions of Sale | D23: N/A | E23: N/A | F23: 0 | G23: None | H23: 0 | I23: None | J23: 0 | K23: None | L23: 0 | M23: None | N23: 0 | O23: N/A | P23: -0.1
C24: Terms/Conditions of Sale Adjusted | F24: =IF(LEFT(CELL("format",F23),1)="P",F22*(1+F23),IF(LEFT(CELL("format",F23),1)="C",F22+F23)) | H24: =IF(LEFT(CELL("format",H23),1)="P",H22*(1+H23),IF(LEFT(CELL("format",H23),1)="C",H22+H23)) | J24: =IF(LEFT(CELL("format",J23),1)="P",J22*(1+J23),IF(LEFT(CELL("format",J23),1)="C",J22+J23)) | L24: =IF(LEFT(CELL("format",L23),1)="P",L22*(1+L23),IF(LEFT(CELL("format",L23),1)="C",L22+L23)) | N24: =IF(LEFT(CELL("format",N23),1)="P",N22*(1+N23),IF(LEFT(CELL("format",N23),1)="C",N22+N23)) | P24: =IF(LEFT(CELL("format",P23),1)="P",P22*(1+P23),IF(LEFT(CELL("format",P23),1)="C",P22+P23))
C25: Expenditures After Sale | D25: N/A | E25: N/A | F25: 0 | G25: None | H25: 0 | I25: None | J25: 0 | K25: None | L25: 0 | M25: None | N25: 0 | O25: N/A | P25: 0
C26: Expenditures After Sale Adjusted | F26: =IF(LEFT(CELL("format",F25),1)="P",F24*(1+F25),IF(LEFT(CELL("format",F25),1)="C",F24+F25)) | H26: =IF(LEFT(CELL("format",H25),1)="P",H24*(1+H25),IF(LEFT(CELL("format",H25),1)="C",H24+H25)) | J26: =IF(LEFT(CELL("format",J25),1)="P",J24*(1+J25),IF(LEFT(CELL("format",J25),1)="C",J24+J25)) | L26: =IF(LEFT(CELL("format",L25),1)="P",L24*(1+L25),IF(LEFT(CELL("format",L25),1)="C",L24+L25)) | N26: =IF(LEFT(CELL("format",N25),1)="P",N24*(1+N25),IF(LEFT(CELL("format",N25),1)="C",N24+N25)) | P26: =IF(LEFT(CELL("format",P25),1)="P",P24*(1+P25),IF(LEFT(CELL("format",P25),1)="C",P24+P25))
C27: Market Conditions | D27: N/A | E27: =E8 | F27: 0 | G27: =G8 | H27: 0 | I27: =I8 | J27: 0 | K27: =K8 | L27: 0 | M27: =M8 | N27: 0.03 | O27: =O8 | P27: 0
C28: Market Conditions Adjusted | F28: =IF(LEFT(CELL("format",F27),1)="P",F26*(1+F27),IF(LEFT(CELL("format",F27),1)="C",F26+F27)) | H28: =IF(LEFT(CELL("format",H27),1)="P",H26*(1+H27),IF(LEFT(CELL("format",H27),1)="C",H26+H27)) | J28: =IF(LEFT(CELL("format",J27),1)="P",J26*(1+J27),IF(LEFT(CELL("format",J27),1)="C",J26+J27)) | L28: =IF(LEFT(CELL("format",L27),1)="P",L26*(1+L27),IF(LEFT(CELL("format",L27),1)="C",L26+L27)) | N28: =IF(LEFT(CELL("format",N27),1)="P",N26*(1+N27),IF(LEFT(CELL("format",N27),1)="C",N26+N27)) | P28: =IF(LEFT(CELL("format",P27),1)="P",P26*(1+P27),IF(LEFT(CELL("format",P27),1)="C",P26+P27))
C29: Total Quantified Adjustment | F29: =IFERROR(TEXT(F28-F17,"$#,##0.00")&CHAR(10)&" or "&CHAR(10)&TEXT((F28-F17)/F17,"0.00%"),0) | H29: =IFERROR(TEXT(H28-H17,"$#,##0.00")&CHAR(10)&" or "&CHAR(10)&TEXT((H28-H17)/H17,"0.00%"),0) | J29: =IFERROR(TEXT(J28-J17,"$#,##0.00")&CHAR(10)&" or "&CHAR(10)&TEXT((J28-J17)/J17,"0.00%"),0) | L29: =IFERROR(TEXT(L28-L17,"$#,##0.00")&CHAR(10)&" or "&CHAR(10)&TEXT((L28-L17)/L17,"0.00%"),0) | N29: =IFERROR(TEXT(N28-N17,"$#,##0.00")&CHAR(10)&" or "&CHAR(10)&TEXT((N28-N17)/N17,"0.00%"),0) | P29: =IFERROR(TEXT(P28-P17,"$#,##0.00")&CHAR(10)&" or "&CHAR(10)&TEXT((P28-P17)/P17,"0.00%"),0)
C30: Quantitatively Adjusted Price | F30: =F28 | H30: =H28 | J30: =J28 | L30: =L28 | N30: =N28 | P30: =P28
C31: Qualitative Adjustments | F31: =SUM(F19:F29)+1 | H31: =SUM(H19:H29)+1 | J31: =SUM(J19:J29)+1 | L31: =SUM(L19:L29)+1 | N31: =SUM(N19:N29)+1 | P31: =SUM(P19:P29)+1
C32: Location | D32: Good | E32: Above-Average | F32: 0.05 | G32: Average | H32: 0.15 | I32: Average | J32: 0.15 | K32: Good | L32: 0.05 | M32: Good | N32: 0.05 | O32: Good | P32: -0.05
C33: Distance from Subject | D33: N/A | E33: 32 miles | G33: 16 miles | I33: 1/4 mile | K33: 1/4 mile | M33: 1/4 mile | O33: 24 miles
C34: Surrounding Land Uses | D34: Retail, residential, office | E34: Residential, retail | G34: Retail, office residential | I34: Retail, Office | K34: Retail, residential | M34: Office, flex, residential | O34: Residential, retail
C35: Quality/Condition of Surrounding Area | D35: Average to Good | E35: Average to Good | G35: Average to Good | I35: Average to Good | K35: Good to New | M35: Good to New | O35: Average to Very Good
C36: Access to Commercial Services/Amenities | D36: Good | E36: Average | G36: Good | I36: Good | K36: Good | M36: Average | O36: Good
C37: Visibility/Access | D37: Good: Primary thoroughfare | E37: Good: Primary thoroughfare | G37: Average: S. Lima St. | I37: Average: Oakridge Dr. & Mcmurry Ave. | K37: Good: Indiana St. & W 64th Ave. | M37: Average: Compark Blvd. | O37: Good - Access & Visibility from E 56th Ave.
C38: Demographics | D38: Population 3-Mile Radius: 60,202 MHHI 3-Mile Radius: $69,785 Pop. Growth (5-Yrs.): 9.65% | E38: Population 3-Miles: 45,519 MHHI 3-Mile Radius: $115,596 Pop. Growth (5-Yrs.): 9.59% | G38: Population 3-Miles: 60,848 MHHI 5-Mile Radius: $94,646 Pop. Growth (5-Yrs.): 6.84% | I38: Population 3-Miles: 83,390 MHHI 3-Mile Radius: $73,915 Pop. Growth (5-Yrs.): 8.97% | K38: Population 3-Miles: 57,214 MHHI 3-Mile Radius: $107,760 Pop. Growth (5-Yrs.): 4.49% | M38: Population 3-Miles: 55,098 MHHI 3-Mile Radius: $99,667 Pop. Growth (5-Yrs.): 9.59% | O38: Population 5-Mile Radius: 219,743 MHHI 3-Mile Radius: $58,707 Population Growth (5 Yrs.): 8.19%
C39: Property Size (SF) | D39: ='Property Info'!B4 | E39: =E13 | F39: 0 | G39: =G13 | H39: 0 | I39: =I13 | J39: 0 | K39: =K13 | L39: 0 | M39: =M13 | N39: -0.05 | O39: =O13 | P39: 0
C40: YOC / Condition | D40: 2019/Good | E40: 2018/Good | F40: 0 | G40: 2008/Above-Average | H40: 0.05 | I40: 2000 (Ren. 2019)/Good | J40: 0 | K40: 2019/New | L40: -0.05 | M40: 2015/Good | N40: 0 | O40: 2019/New | P40: 0
C41: Quality | D41: Good | E41: Average | F41: 0 | G41: Average | H41: 0 | I41: Average | J41: 0 | K41: Average | L41: 0 | M41: Average | N41: 0 | O41: Average | P41: 0
C42: Frame | D42: Woodf-frame | E42: Concrete, Masonry | G42: Wood | I42: Wood-frame, masonry | K42: Wood-frame | M42: Wood-frame | O42: Wood
C43: Exterior | D43: Stucco, brick | E43: Metal, painted concrete | G43: Wood | I43: Brick, wood siding | K43: Wood, brick | M43: Wood, brick | O43: Wood, stucco
C44: Architectural Styling | D44: Daycare building | E44: Store Building | G44: Daycare building | I44: Daycare building | K44: Daycare/School Building | M44: Daycare/School Building | O44: Franchise daycare
C45: Typical Interior Finishes | D45: Good-quality daycare | E45: Average-quality school | G45: Average-quality daycare | I45: Average-quality daycare | K45: Average-quality daycare | M45: Average-quality daycare | O45: Average quality daycare/school finishes
C46: Parking Ratio (Per 1,000 SF) | D46: =(D15/D13)*1000 | E46: =(E15/E13)*1000 | F46: 0 | G46: =(G15/G13)*1000 | H46: -0.05 | I46: =(I15/I13)*1000 | J46: -0.05 | K46: =(K15/K13)*1000 | L46: 0 | M46: =(M15/M13)*1000 | N46: -0.05 | O46: =(O15/O13)*1000 | P46: 0
C47: Tenancy / Occupancy | D47: Good | E47: Average | F47: 0 | G47: Good | H47: -0.1 | I47: Average | J47: 0 | K47: Above-Average | L47: -0.05 | M47: Above-Average | N47: -0.05 | O47: Good | P47: 0
C48: Occupancy | D48: 1 | E48: 1 | G48: 1 | I48: 1 | K48: 1 | M48: 1 | O48: 1
C49: Tenant Risk | D49: National Daycare Franchise | E49: Parker Performaing Arts | G49: Goddard School | I49: Local daycare tenant | K49: Learning Experence (Local Franchise) | M49: Learning Experence (Local Franchise) | O49: Low - Franchise Daycare
C50: Overall Cap Rate | D50: N/A | E50: N/A | G50: N/A | I50: N/A | K50: 0.0715 | M50: 0.0675 | O50: 0.0635
C51: Years Remaining | D51: 15 | E51: 15 | G51: 6 | I51: N/A | K51: N/A | M51: N/A | O51: 15
C52: Renewal Options | D52: 2 | E52: 3 | G52: 3 | I52: N/A | K52: N/A | M52: N/A | O52: 3
C53: Functional Utility | D53: Average | E53: Below-Average | F53: 0 | G53: Average | H53: -0.05 | I53: Average | J53: -0.05 | K53: Average | L53: -0.05 | M53: Average | N53: -0.05 | O53: Good | P53: -0.1
C54: Building Layout | D54: Single-level, good | E54: Two-stories, good | G54: Single-level, good | I54: Single-story Residential Conversion | K54: Single-story Residential Conversion | M54: Single-story Residential Conversion | O54: Single-level, good
C55: Building Amenities | D55: Perimiter classrooms, office, laundry, kitchen | E55: Calssrooms, gym, offices, cafateria, auditorium. | G55: Perimiter classrooms, office, laundry | I55: Classrooms, office, kitchen | K55: Classrooms, office, kitchen | M55: Classrooms, office, kitchen | O55: Commercial kitchen, office, meeting room, teacher's lounge.
C56: Above/Below Grade Space | D56: All above | E56: All above | G56: All above | I56: All above | K56: All above | M56: All above | O56: All above
C57: Site Improvements, Other | D57: Multiple playgrounds | E57: Multiple playgrounds | G57: Multiple playgrounds | I57: Multiple playgrounds | K57: Multiple playgrounds | M57: Multiple playgrounds | O57: Multiple playgrounds, large outdoor activity areas.
C58: Total Non Quantified Adj. | F58: =SUM(F32:F41,F46:F47,F53) | H58: =SUM(H32,H39,H40,H41,H46,H47,H53) | J58: =SUM(J32,J39,J40,J41,J46,J47,J53) | L58: =SUM(L32,L39,L40,L41,L46,L47,L53) | N58: =SUM(N32,N39,N40,N41,N46,N47,N53) | P58: =SUM(P32,P39,P40,P41,P46,P47,P53)
C59: Indication for Subject: | F59: =IF(LEFT(CELL("format",F58),1)="P",F30*(1+F58),IF(LEFT(CELL("format",F58),1)="C",F30+F58)) | H59: =IF(LEFT(CELL("format",H58),1)="P",H30*(1+H58),IF(LEFT(CELL("format",H58),1)="C",H30+H58)) | J59: =IF(LEFT(CELL("format",J58),1)="P",J30*(1+J58),IF(LEFT(CELL("format",J58),1)="C",J30+J58)) | L59: =IF(LEFT(CELL("format",L58),1)="P",L30*(1+L58),IF(LEFT(CELL("format",L58),1)="C",L30+L58)) | N59: =IF(LEFT(CELL("format",N58),1)="P",N30*(1+N58),IF(LEFT(CELL("format",N58),1)="C",N30+N58)) | P59: =IF(LEFT(CELL("format",P58),1)="P",P30*(1+P58),IF(LEFT(CELL("format",P58),1)="C",P30+P58))
E60: =(E39-$D$39)/$D$39 | G60: =(G39-$D$39)/$D$39 | I60: =(I39-$D$39)/$D$39 | K60: =(K39-$D$39)/$D$39 | M60: =(M39-$D$39)/$D$39
E61: 195
D62: Rounded Value | E62: =MROUND(E61*D39,5000)
D63: Value PSF | E63: =E62/D39
D64: Income | E64: ='IA Values'!H13
E67: 262.27
E68: 247.3 | F68: =(E67-E68)/E68

Sheet LA
B2: LEASE ABSTRACT
B3: Lessor | C3: Yafa Realty Investments, LLC | G3: Annual Rent Calc. Table
B4: Lessee | C4: Walker Component Group, Inc. | G4: Month | H4: Monthly Rent
B5: Building Size (SF) | C5: 33750 | G5: January | H5: 16120
B6: Lease Sign Date | C6: 42689 | G6: February | H6: 16120
B7: Lease Commencement Date | C7: 42689 | G7: March | H7: 16120
B8: Lease Expiration Date | C8: 46752 | G8: April | H8: 16120
B9: Base Lease Term (Months) | C9: =+(C8-C7)/365*12 | G9: May | H9: 16120
B10: 12 Months Contract Rental Income (Jan-Dec 2020) | C10: =H17 | G10: June | H10: 16120
B11: 12 Months Contract Rental Income (Jan-Dec 2020) | C11: =C10/C5 | G11: July | H11: 16120
B12: Base Rents | D12: Annual Rent (Lease) | G12: August | H12: 20230
B13: Year 1 (11/16-10/17) | C13: =D13/$C$5 | D13: 194062.5 | G13: September | H13: 20230
B14: Year 2 (11/17-10/18) | C14: =D14/$C$5 | D14: 194062.5 | G14: October | H14: 20230
B15: Year 3 (11/18-10/19) | C15: =D15/$C$5 | D15: 202500 | G15: November | H15: 20230
B16: Year 4 (11/19-10/20) | C16: =D16/$C$5 | D16: 202500 | G16: December | H16: 20230
B17: Year 5 (11/20-10/21) | C17: =D17/$C$5 | D17: 210937.5 | G17: Total | H17: =SUM(H5:H16)
B18: Frist Renewal Period | G18: PSF | H18: =H17/FE!C14
B19: Year 6 | C19: =D19/$C$5 | D19: 210937.5
B20: Year 7 | C20: =D20/$C$5 | D20: 219375
B21: Year 8 | C21: =D21/$C$5 | D21: 226125
B22: Year 9 | C22: =D22/$C$5 | D22: 232875
B23: Year 10 | C23: =D23/$C$5 | D23: 239625
B24: Year 11 | C24: =D24/$C$5 | D24: 242988
B29: Expense Structure | C29: NNN
B30: Landlord Expense Responsibilities | C30: Roof replacement/repair, structural damage
B31: Tenant Expense Responsibilities | C31: Tenant is responsible for all expenses directly, including taxes, insurance, CAM/repairs & maintenance, utilities and other expenses.
B32: Comments | C32: Initial 5-year term with two 5-year renewal options. First renewal option started as of the valuation date.
B33: Purchase Options | C33: None
B34: Termination Clause | C34: None
B35: Guarantor | C35: None
B36: Other | C36: Triple net agreement, sale-leaseback.
B37: Source | C37: Lease Agreement, owner, inspection, assessor data

Sheet LAG Percent
A2: COMPARABLE LEASE ADJUSTMENT GRID
A3: Characteristics | C3: Subject | E3: Lease 1 | G3: Lease 2 | I3: Lease 3 | K3: Lease 4 | M3: Rent 5
A4: Address | C4: ='Property Info'!B16 | E4: 5676 N Pecos Street | G4: 5100 Fox Street | I4: 5151 Bannock Street | K4: 4715 Colorado Blvd. | M4: 5882 South Youngfield Court
A5: City | C5: ='Property Info'!B17 | E5: Denver, CO | G5: Denver, CO | I5: Denver, CO | K5: Denver, CO | M5: Littleton, CO
A6: Distance from Subject | C6: N/A | E6: 1 mile | G6: 1 mile | I6: 1 mile | K6: 1/4 mile | M6: 1 mile
A7: Data Source | C7: ='Detailed Sales Grid'!D12 | E7: CoStar, Assessor, OM | G7: CoStar, Assessor, OM | I7: CoStar, Assessor, OM | K7: CoStar, Broker, Listing | M7: CoStar, Assessor
A8: Proximity to Subject | C8: N/A | E8: 1.5 miles | G8: 1.5 miles | I8: 1.5 miles | K8: 5.0 miles | M8: 3.0 miles
A9: Building Size | C9: ='Property Info'!B4 | E9: 29050 | G9: 40811 | I9: 20000 | K9: 37044 | M9: 7786
A10: Vacancy | C10: 0 | D10: =C10/C9 | E10: 0 | F10: 0 | G10: 0 | H10: 0 | I10: 0 | J10: 0 | K10: 0 | L10: 0 | M10: 0 | N10: 0
A11: Parking Ratio | C11: 27 | D11: =ROUND((C11/C9)*1000,2)&":1,000SF" | E11: 19 | F11: =ROUND((E11/E9)*1000,2)&":1,000SF" | G11: 19 | H11: =ROUND((G11/G9)*1000,2)&":1,000SF" | I11: 19 | J11: =ROUND((I11/I9)*1000,2)&":1,000SF" | K11: 19 | L11: =ROUND((K11/K9)*1000,2)&":1,000SF" | M11: 19 | N11: =ROUND((M11/M9)*1000,2)&":1,000SF"
A12: Representative Lease
A13: Actual or Asking Lease Rate | C13: N/A | E13: Actual | G13: Actual | I13: Actual | K13: Actual | M13: Actual
A14: Tenant | C14: =LA!C4 | E14: Four Star Drywall | G14: Marcone Supply | I14: Local Industrial User | K14: Brow 1, LLC | M14: Maypoint Learning Center
A15: SF Area Leased | C15: ='Property Info'!B4 | E15: =E9 | G15: 22248 | I15: 20000 | K15: 37044 | M15: =M9
A16: Commencement | C16: 44515 | E16: 43781 | G16: 43731 | I16: 43617 | K16: 43601 | M16: 43490
A17: Term | C17: 6 Years | E17: 3 Years | G17: 5 Years | I17: 3 Years | K17: 3 Years | M17: 5 Years
A18: TI Allowance | C18: N/A | E18: N/R | G18: N/R | I18: N/R | K18: N/R | M18: N/R
A19: Lease Rate Expense Structure | C19: NNN | E19: NNN | G19: NNN | I19: NNN | K19: NNN | M19: NNN
A20: Base Annual Rent | C20: =LA!C11 | E20: 11 | G20: 7.95 | I20: 12 | K20: 9.5 | M20: 22
A21: Expense Adjustments | C21: N/A | E21: 0 | G21: 0 | I21: 0 | K21: 0 | M21: 0
A22: Adjusted Rent (NNN) | C22: =C20 | E22: =E20+E21 | G22: =G20+G21 | I22: =I20+I21 | K22: =K20+K21 | M22: =M20+M21
A23: Adjustments | C23: Description | E23: Description | F23: Adj. | G23: Description | H23: Adj. | I23: Description | J23: Adj. | K23: Description | L23: Adj. | M23: Description | N23: Adj.
A24: Market Trends | C24: N/A | E24: =E16 | F24: 0 | G24: =G16 | H24: 0 | I24: =I16 | J24: 0 | K24: =K16 | L24: 0 | M24: =M16 | N24: 0.1
A25: Economics/Tenancy | C25: Industrial, Average Credit Risk | E25: Industrial, Average Credit Risk | F25: 0 | G25: Industrial, Average Credit Risk | H25: 0 | I25: Industrial, Average Credit Risk | J25: 0 | K25: Industrial, Average Credit Risk | L25: 0 | M25: Local Tenant - Good Quality | N25: 0.1
A26: Location | C26: =Export030823!R2 | E26: Average | F26: 0 | G26: Average | H26: 0 | I26: Average | J26: 0 | K26: Average | L26: 0 | N26: 0
A27: Age/Condition | C27: =Export030823!T2 | E27: 1972/Average | F27: 0 | G27: 1971/Fair | H27: 0.1 | I27: 1922 (Ren.)/ Above-Average | J27: -0.05 | K27: 1954/Average | L27: 0 | M27: 2014 (Ren.)/Above-Average | N27: 0.1
A28: Size (SF) | C28: =C15 | E28: =E15 | F28: 0 | G28: =G15 | H28: -0.05 | I28: =I15 | J28: -0.05 | K28: =K15 | L28: 0 | M28: =M15 | N28: -0.05
A29: Quality | C29: =Export030823!U2 | E29: Average | F29: 0 | G29: Average | H29: 0 | I29: Average | J29: 0 | K29: Average | L29: 0 | M29: Good | N29: 0
A30: Land-To-Building Ratio | C30: =Export030823!V2 | E30: =75359/E9 | F30: 0 | G30: =143748/G9 | H30: 0 | I30: =87120/I9 | J30: 0 | K30: =91912/K9 | L30: 0 | M30: 5.52 | N30: -0.05
A31: Functional Utility | C31: =Export030823!X2 | E31: Good: I-3 Zoning | F31: -0.1 | G31: Average | H31: 0 | I31: Above-Average: I-B Zoning | J31: -0.05 | K31: Average | L31: 0 | M31: Average | N31: 0
A32: Subtotal Net Adjustments | F32: =SUM(F24:F31) | H32: =SUM(H24:H31) | J32: =SUM(J24:J31) | L32: =SUM(L24:L31) | N32: =SUM(N24:N31)
A33: Adjusted Lease Rate Per Square Foot | F33: =+E22*(1+F32) | H33: =+G22*(1+H32) | J33: =+I22*(1+J32) | L33: =+K22*(1+L32) | N33: =+M22*(1+N32)
F36: =F33
F37: =H33
F38: =J33
F39: =L33
E41: =(E28-$C$28)/$C$28 | G41: =(G28-$C$28)/$C$28 | I41: =(I28-$C$28)/$C$28 | K41: =(K28-$C$28)/$C$28

Sheet IS Summary
C3: SUMMARY OF IMPROVED SALES
C4: No. | D4: Type | E4: Property Type / Location | F4: Date of Sale | G4: Property Rights | H4: Year Built | I4: Bldg. Size (SF) | J4: Site Size (SF) (Acres) | K4: Building Footprint | L4: Coverage Ratio | M4: Percent Office | N4: Clear Heights (ft.) | O4: Occupancy | P4: Sale Price | Q4: Price PSF | R4: Overall Rate
C5: =ROW()-4 | D5: Sale | E5: Industrial | F5: 42705 | G5: Fee Simple | H5: 2007 | I5: 25540 | J5: 214163 | K5: 25540 | L5: =K5/J5 | M5: 0.14 | N5: 20' | O5: Vacant at TOS | P5: 1800000 | Q5: =P5/I5 | R5: N/A
E6: 61 Chimuza Road | J6: =J5/43560
E7: Rock Springs, Wyoming
C9: 2 | D9: Sale | E9: Industrial | F9: 42583 | G9: Fee Simple | H9: 2005 | I9: 13100 | J9: 138956 | K9: 13100 | L9: =K9/J9 | M9: 0.21 | N9: 20' | O9: Vacant at TOS | P9: 1350000 | Q9: =P9/I9 | R9: N/A
E10: 1751 Blairtown Road | J10: =J9/43560
E11: Rock Springs, Wyoming
C13: 3 | D13: Sale | E13: Industrial | F13: 42461 | G13: Fee Simple | H13: 1981 | I13: 8000 | J13: 50006 | K13: 8000 | L13: =K13/J13 | M13: 0.1 | N13: 16' | O13: Vacant at TOS | P13: 530000 | Q13: =P13/I13 | R13: 0.074
E14: 6 Bowker Road | J14: =J13/43560
E15: Rock Springs, Wyoming
C17: 4 | D17: Sale | E17: Industrial | F17: 42430 | G17: Fee Simple | H17: 1979 | I17: 5300 | J17: 87555 | K17: 5300 | L17: =K17/J17 | M17: 0.15 | N17: 16' | O17: Vacant at TOS | P17: 417000 | Q17: =P17/I17 | R17: 0.065
E18: 1931 Yellowstone Road | J18: =J17/43560
E19: Rock Springs, Wyoming
C21: 5 | D21: Sale | E21: Industrial | F21: 42401 | G21: Fee Simple | H21: 1978 | I21: 7500 | J21: 29620 | K21: 7500 | L21: =K21/J21 | M21: 0.15 | N21: 18' | O21: Vacant at TOS | P21: 400000 | Q21: =P21/I21 | R21: 0.055
E22: 60 Signal Road | J22: =J21/43560
E23: Rock Springs, Wyoming
C25: Subj. | E25: ='Property Info'!B15 | H25: ='Property Info'!B8 | I25: ='Property Info'!B4 | J25: ='Property Info'!B11 | K25: ='Property Info'!B5 | L25: ='Property Info'!B13 | M25: ='Property Info'!B14 | O25: ='Property Info'!B19
E26: ='Property Info'!B16 | J26: ='Property Info'!B12
E27: ='Property Info'!B17

Sheet HOA
C2: HISTORICAL OPERATING ANALYSIS
AA3: =LA!C5
D4: 2013 | G4: 2014 | J4: 2015 | M4: 2016 | P4: 2017 | S4: Budget | V4: BBG Projection*
D5: Total | E5: per SF | G5: Total | H5: per SF | J5: Total | K5: per SF | M5: Total | N5: per SF | P5: Total | Q5: per SF | S5: Total | T5: per SF | V5: Total | W5: per SF
C6: Rental Income | D6: =SUMIF(Category,$B6,AMTY1) | E6: =D6/NRA | G6: =SUMIF(Category,$B6,AMTY2) | H6: =G6/NRA | J6: =SUMIF(Category,$B6,AMTY3) | K6: =J6/NRA | M6: 122101.44 | N6: =M6/$AA$3 | P6: 185866.52 | Q6: =P6/$AA$3 | S6: =SUMIF(Category,$B6,AmtBdgt) | T6: =S6/NRA | V6: =[3]ProForma!C3 | W6: =V6/NRA
C7: Operating Expense Recoveries | D7: =SUMIF(Category,$B7,AMTY1) | E7: =D7/NRA | G7: =SUMIF(Category,$B7,AMTY2) | H7: =G7/NRA | J7: =SUMIF(Category,$B7,AMTY3) | K7: =J7/NRA | M7: 80407.76 | N7: =M7/$AA$3 | P7: 101239 | Q7: =P7/$AA$3 | S7: =SUMIF(Category,$B7,AmtBdgt) | T7: =S7/NRA | V7: =[3]ProForma!C4 | W7: =V7/NRA
C8: Parking | D8: =SUMIF(Category,$B8,AMTY1) | E8: =D8/NRA | G8: =SUMIF(Category,$B8,AMTY2) | H8: =G8/NRA | J8: =SUMIF(Category,$B8,AMTY3) | K8: =J8/NRA | M8: =SUMIF(Category,$B8,AMTY4) | N8: =M8/$AA$3 | P8: =SUMIF(Category,$B8,AMTY5) | Q8: =P8/$AA$3 | S8: =SUMIF(Category,$B8,AmtBdgt) | T8: =S8/NRA | V8: =W8*NRA | W8: 0
C9: Late Charges | D9: =SUMIF(Category,$B9,AMTY1) | E9: =D9/NRA | G9: =SUMIF(Category,$B9,AMTY2) | H9: =G9/NRA | J9: =SUMIF(Category,$B9,AMTY3) | K9: =J9/NRA | M9: =SUMIF(Category,$B9,AMTY4) | N9: =M9/$AA$3 | P9: =SUMIF(Category,$B9,AMTY5) | Q9: =P9/$AA$3 | S9: =SUMIF(Category,$B9,AmtBdgt) | T9: =S9/NRA | V9: =W9*NRA | W9: 0
C10: NSF Fee Income | D10: =SUMIF(Category,$B10,AMTY1) | E10: =D10/NRA | G10: =SUMIF(Category,$B10,AMTY2) | H10: =G10/NRA | J10: =SUMIF(Category,$B10,AMTY3) | K10: =J10/NRA | M10: =SUMIF(Category,$B10,AMTY4) | N10: =M10/$AA$3 | P10: =SUMIF(Category,$B10,AMTY5) | Q10: =P10/$AA$3 | S10: =SUMIF(Category,$B10,AmtBdgt) | T10: =S10/NRA | V10: =W10*NRA | W10: 0
C11: Keys, Lock, Lock Charge | D11: =SUMIF(Category,$B11,AMTY1) | E11: =D11/NRA | G11: =SUMIF(Category,$B11,AMTY2) | H11: =G11/NRA | J11: =SUMIF(Category,$B11,AMTY3) | K11: =J11/NRA | M11: =SUMIF(Category,$B11,AMTY4) | N11: =M11/$AA$3 | P11: =SUMIF(Category,$B11,AMTY5) | Q11: =P11/$AA$3 | S11: =SUMIF(Category,$B11,AmtBdgt) | T11: =S11/NRA | V11: =W11*NRA | W11: 0
C12: Lease Termination Fee Income | D12: =SUMIF(Category,$B12,AMTY1) | E12: =D12/NRA | G12: =SUMIF(Category,$B12,AMTY2) | H12: =G12/NRA | J12: =SUMIF(Category,$B12,AMTY3) | K12: =J12/NRA | M12: =SUMIF(Category,$B12,AMTY4) | N12: =M12/$AA$3 | P12: =SUMIF(Category,$B12,AMTY5) | Q12: =P12/$AA$3 | S12: =SUMIF(Category,$B12,AmtBdgt) | T12: =S12/NRA | V12: =W12*NRA | W12: 0
C13: Legal and Collection Fee Income | D13: =SUMIF(Category,$B13,AMTY1) | E13: =D13/NRA | G13: =SUMIF(Category,$B13,AMTY2) | H13: =G13/NRA | J13: =SUMIF(Category,$B13,AMTY3) | K13: =J13/NRA | M13: =SUMIF(Category,$B13,AMTY4) | N13: =M13/$AA$3 | P13: =SUMIF(Category,$B13,AMTY5) | Q13: =P13/$AA$3 | S13: =SUMIF(Category,$B13,AmtBdgt) | T13: =S13/NRA | V13: =W13*NRA | W13: 0
C14: Storage Space Rental | D14: =SUMIF(Category,$B14,AMTY1) | E14: =D14/NRA | G14: =SUMIF(Category,$B14,AMTY2) | H14: =G14/NRA | J14: =SUMIF(Category,$B14,AMTY3) | K14: =J14/NRA | M14: =SUMIF(Category,$B14,AMTY4) | N14: =M14/$AA$3 | P14: =SUMIF(Category,$B14,AMTY5) | Q14: =P14/$AA$3 | S14: =SUMIF(Category,$B14,AmtBdgt) | T14: =S14/NRA | V14: =W14*NRA | W14: 0
C15: Miscellaneous | D15: =SUMIF(Category,$B15,AMTY1) | E15: =D15/NRA | G15: =SUMIF(Category,$B15,AMTY2) | H15: =G15/NRA | J15: =SUMIF(Category,$B15,AMTY3) | K15: =J15/NRA | M15: =SUMIF(Category,$B15,AMTY4) | N15: =M15/$AA$3 | P15: =SUMIF(Category,$B15,AMTY5) | Q15: =P15/$AA$3 | S15: =SUMIF(Category,$B15,AmtBdgt) | T15: =S15/NRA | V15: =[3]ProForma!C7 | W15: =V15/NRA
C16: Total Potential Gross Income | D16: =SUM(D6:D15) | E16: =D16/NRA | G16: =SUM(G6:G15) | H16: =G16/NRA | J16: =SUM(J6:J15) | K16: =J16/NRA | M16: =SUM(M6:M15) | N16: =M16/$AA$3 | P16: =SUM(P6:P15) | Q16: =P16/$AA$3 | S16: =SUM(S6:S15) | T16: =S16/NRA | V16: =SUM(V6:V15) | W16: =V16/NRA
N17: =M17/$AA$3 | Q17: =P17/$AA$3
C18: Physical Vacancy | D18: =SUMIF(Category,$B18,AMTY1) | E18: =D18/NRA | G18: =SUMIF(Category,$B18,AMTY2) | H18: =G18/NRA | J18: =SUMIF(Category,$B18,AMTY3) | K18: =J18/NRA | M18: =SUMIF(Category,$B18,AMTY4) | N18: =M18/$AA$3 | P18: =SUMIF(Category,$B18,AMTY5) | Q18: =P18/$AA$3 | S18: =SUMIF(Category,$B18,AmtBdgt) | T18: =S18/NRA
C19: Bad Debt / Collection Loss | D19: =SUMIF(Category,$B19,AMTY1) | E19: =D19/NRA | G19: =SUMIF(Category,$B19,AMTY2) | H19: =G19/NRA | J19: =SUMIF(Category,$B19,AMTY3) | K19: =J19/NRA | M19: =SUMIF(Category,$B19,AMTY4) | N19: =M19/$AA$3 | P19: =SUMIF(Category,$B19,AMTY5) | Q19: =P19/$AA$3 | S19: =SUMIF(Category,$B19,AmtBdgt) | T19: =S19/NRA
C20: Concessions | D20: =SUMIF(Category,$B20,AMTY1) | E20: =D20/NRA | G20: =SUMIF(Category,$B20,AMTY2) | H20: =G20/NRA | J20: =SUMIF(Category,$B20,AMTY3) | K20: =J20/NRA | M20: =SUMIF(Category,$B20,AMTY4) | N20: =M20/$AA$3 | P20: =SUMIF(Category,$B20,AMTY5) | Q20: =P20/$AA$3 | S20: =SUMIF(Category,$B20,AmtBdgt) | T20: =S20/NRA
C21: Vacancy & Collection Loss | D21: =-[3]OpActuals!B13 | E21: =D21/NRA | G21: =-[3]OpActuals!C13 | H21: =G21/NRA | J21: =-[3]OpActuals!D13 | K21: =J21/NRA | M21: =-[3]OpActuals!E13 | N21: =M21/$AA$3 | P21: =-[3]OpActuals!G13 | Q21: =P21/$AA$3 | S21: =-[3]OpActuals!H13 | T21: =S21/NRA
C22: EFFECTIVE GROSS INCOME | D22: =D16+D21 | E22: =D22/NRA | G22: =G16+G21 | H22: =G22/NRA | J22: =J16+J21 | K22: =J22/NRA | M22: =SUM(M6:M7) | N22: =M22/$AA$3 | P22: =SUM(P6:P7) | Q22: =P22/$AA$3 | S22: =S16+S21 | T22: =S22/NRA | V22: =[3]ProForma!C11 | W22: =V22/NRA
C23: Fixed Expenses
C24: Real Estate Taxes | D24: =SUMIF(Category,$B24,AMTY1) | E24: =D24/NRA | G24: =SUMIF(Category,$B24,AMTY2) | H24: =G24/NRA | J24: =SUMIF(Category,$B24,AMTY3) | K24: =J24/NRA | M24: 58886 | N24: =M24/$AA$3 | P24: 60666.21 | Q24: =P24/$AA$3 | S24: =SUMIF(Category,$B24,AmtBdgt) | T24: =S24/NRA | V24: =W24*NRA | W24: 0
C25: Property Insurance | D25: =SUMIF(Category,$B25,AMTY1) | E25: =D25/NRA | G25: =SUMIF(Category,$B25,AMTY2) | H25: =G25/NRA | J25: =SUMIF(Category,$B25,AMTY3) | K25: =J25/NRA | M25: 6547.2 | N25: =M25/$AA$3 | P25: 7893.9 | Q25: =P25/$AA$3 | S25: =SUMIF(Category,$B25,AmtBdgt) | T25: =S25/NRA | V25: =W25*NRA | W25: 0
C26: Variable Expenses
C27: Utilities | D27: =SUMIF(Category,$B27,AMTY1) | E27: =D27/NRA | G27: =SUMIF(Category,$B27,AMTY2) | H27: =G27/NRA | J27: =SUMIF(Category,$B27,AMTY3) | K27: =J27/NRA | M27: 3705.88 | N27: =M27/$AA$3 | P27: 3936 | Q27: =P27/$AA$3 | S27: =SUMIF(Category,$B27,AmtBdgt) | T27: =S27/NRA | V27: =W27*NRA | W27: =[3]SummaryExpenseTbl!M32
C28: CAM Repairs & Maintenance | D28: =SUMIF(Category,$B28,AMTY1) | E28: =D28/NRA | G28: =SUMIF(Category,$B28,AMTY2) | H28: =G28/NRA | J28: =SUMIF(Category,$B28,AMTY3) | K28: =J28/NRA | M28: 89936 | N28: =M28/$AA$3 | P28: 10029 | Q28: =P28/$AA$3 | S28: =SUMIF(Category,$B28,AmtBdgt) | T28: =S28/NRA | V28: =W28*NRA | W28: 0
C29: Administrative and General | D29: =SUMIF(Category,$B29,AMTY1) | E29: =D29/NRA | G29: =SUMIF(Category,$B29,AMTY2) | H29: =G29/NRA | J29: =SUMIF(Category,$B29,AMTY3) | K29: =J29/NRA | M29: 14390 | N29: =M29/$AA$3 | P29: 1852 | Q29: =P29/$AA$3 | S29: =SUMIF(Category,$B29,AmtBdgt) | T29: =S29/NRA | V29: =W29*NRA | W29: 0
C30: Management | D30: =SUMIF(Category,$B30,AMTY1) | E30: =D30/NRA | G30: =SUMIF(Category,$B30,AMTY2) | H30: =G30/NRA | J30: =SUMIF(Category,$B30,AMTY3) | K30: =J30/NRA | M30: 5399.91 | N30: =M30/$AA$3 | P30: 10656.65 | Q30: =P30/$AA$3 | S30: =SUMIF(Category,$B30,AmtBdgt) | T30: =S30/NRA | V30: =W30*NRA | W30: =[3]SummaryExpenseTbl!M38
C31: Replacement Reserves | D31: =SUMIF(Category,$B31,AMTY1) | E31: =D31/NRA | G31: =SUMIF(Category,$B31,AMTY2) | H31: =G31/NRA | J31: =SUMIF(Category,$B31,AMTY3) | K31: =J31/NRA | M31: =SUMIF(Category,$B31,AMTY4) | N31: =M31/$AA$3 | P31: =SUMIF(Category,$B31,AMTY5) | Q31: =P31/$AA$3 | S31: =SUMIF(Category,$B31,AmtBdgt) | T31: =S31/NRA | V31: =W31*NRA | W31: =[3]SummaryExpenseTbl!M41
C33: TOTAL EXPENSES | D33: =SUM(D24:D25,D27:D31) | E33: =D33/NRA | G33: =SUM(G24:G25,G27:G31) | H33: =G33/NRA | J33: =SUM(J24:J25,J27:J31) | K33: =J33/NRA | M33: =SUM(M24:M25,M27:M30) | N33: =M33/$AA$3 | P33: =SUM(P24:P25,P27:P30) | Q33: =P33/$AA$3 | S33: =SUM(S24:S25,S27:S31) | T33: =S33/NRA | V33: =SUM(V24:V25,V27:V31) | W33: =V33/NRA
C35: NET OPERATING INCOME (NOI) | D35: =D22-D33 | E35: =D35/NRA | G35: =G22-G33 | H35: =G35/NRA | J35: =J22-J33 | K35: =J35/NRA | M35: =M22-M33 | N35: =M35/$AA$3 | P35: =P22-P33 | Q35: =P35/$AA$3 | S35: =S22-S33 | T35: =S35/NRA | V35: =V22-V33 | W35: =V35/NRA

Sheet CED
D2: COMPARABLE EXPENSES DATA
D3: Comparable No. | E3: 1 | H3: 2 | K3: 3 | N3: 3
D4: City | E4: Phoenix | F4: Highlands Ranch | H4: Phoenix | I4: Denver | K4: Phoenix | L4: Arvada | N4: Denver
D5: Year Built | E5: 2002 | F5: 2005 | H5: 2005 | I5: 1964, 1998 | K5: 2007 | L5: 2018 | N5: 1999
D6: Rentable Area | E6: 78150 | F6: 10000 | H6: 8181 | I6: 5627 | K6: 15000 | L6: 10000 | N6: 107760 | T6: Cmp1 | U6: Cmp2 | V6: Cmp3 | W6: Cmp4 | X6: Min | Y6: Max | AA6: Range | AB6: Avg
D7: Year Operations | E7: 2016 | F7: 2019 | H7: 2016 | I7: 2020 | K7: 2016 | L7: 2020 | N7: 2016
D8: Occupancy | E8: 1 | F8: 1 | H8: 1 | I8: 1 | K8: 1 | L8: 1 | N8: 1
D9: Expenses
D10: Real Estate Taxes | E10: 43077 | F10: 4.5 | H10: 302806 | I10: 6.78 | K10: 49012 | L10: 2.75 | N10: 302806 | O10: =N10/N6 | Q10: =AVERAGE(F10,I10,L10) | T10: =F10 | U10: =I10 | V10: =L10 | W10: =IF(ISERROR(Q24),"",IF(Q24=0,"",Q24)) | X10: =MIN(T10:W10) | Y10: =MAX(T10:W10) | AA10: =IF(X10=Y10,TEXT(X10,"$0.00;;-"),CONCATENATE(TEXT(X10,"$0.00;;-"),"–",TEXT(Y10,"$0.00;;-"))) | AB10: =AVERAGE(T10:W10)
D11: Insurance | E11: 4426 | F11: 0.72 | H11: 10776 | I11: 1.5 | K11: 7129 | L11: 1.35 | N11: 10776 | O11: =N11/N6 | Q11: =AVERAGE(F11,I11,L11) | T11: =F11 | U11: =I11 | V11: =L11 | W11: =IF(ISERROR(Q25),"",IF(Q25=0,"",Q25)) | X11: =MIN(T11:W11) | Y11: =MAX(T11:W11) | AA11: =IF(X11=Y11,TEXT(X11,"$0.00;;-"),CONCATENATE(TEXT(X11,"$0.00;;-"),"–",TEXT(Y11,"$0.00;;-"))) | AB11: =AVERAGE(T11:W11)
D12: Utilities | E12: 0 | F12: 1.5 | H12: 0 | I12: 2.23 | K12: 2896 | L12: 1.75 | N12: 0 | O12: =N12/N6 | T12: =F12 | U12: =I12 | V12: =L12 | W12: =IF(ISERROR(Q26),"",IF(Q26=0,"",Q26)) | X12: =MIN(T12:W12) | Y12: =MAX(T12:W12) | AA12: =IF(X12=Y12,TEXT(X12,"$0.00;;-"),CONCATENATE(TEXT(X12,"$0.00;;-"),"–",TEXT(Y12,"$0.00;;-"))) | AB12: =AVERAGE(T12:W12)
D13: CAM Repairs and Maintenace | E13: 16761 | F13: 2 | H13: 84053 | I13: 1.5 | K13: 16040 | L13: 1 | N13: 84053 | O13: =N13/N6 | T13: =F13 | U13: =I13 | V13: =L13 | W13: =IF(ISERROR(Q27),"",IF(Q27=0,"",Q27)) | X13: =MIN(T13:W13) | Y13: =MAX(T13:W13) | AA13: =IF(X13=Y13,TEXT(X13,"$0.00;;-"),CONCATENATE(TEXT(X13,"$0.00;;-"),"–",TEXT(Y13,"$0.00;;-"))) | AB13: =AVERAGE(T13:W13)
D14: Administrative and General | E14: 0 | F14: =E14/E6 | H14: 0 | I14: =H14/H6 | K14: 0 | L14: =K14/K6 | N14: 0 | O14: =N14/N6 | T14: =F14 | U14: =I14 | V14: =L14 | W14: =IF(ISERROR(Q28),"",IF(Q28=0,"",Q28)) | X14: =MIN(T14:W14) | Y14: =MAX(T14:W14) | AA14: =IF(X14=Y14,TEXT(X14,"$0.00;;-"),CONCATENATE(TEXT(X14,"$0.00;;-"),"–",TEXT(Y14,"$0.00;;-"))) | AB14: =AVERAGE(T14:W14)
D15: Management | E15: 7103 | F15: N/R | H15: 30173 | I15: N/R | K15: 0 | L15: N/R | N15: 30173 | O15: =N15/N6 | T15: =F15 | U15: =I15 | V15: =L15 | W15: =IF(ISERROR(Q29),"",IF(Q29=0,"",Q29)) | X15: =MIN(T15:W15) | Y15: =MAX(T15:W15) | AA15: =IF(X15=Y15,TEXT(X15,"$0.00;;-"),CONCATENATE(TEXT(X15,"$0.00;;-"),"–",TEXT(Y15,"$0.00;;-"))) | AB15: =AVERAGE(T15:W15)
D16: Replacement Reserves | E16: 0 | F16: =E16/E6 | H16: 0 | I16: =H16/H6 | K16: 0 | L16: =K16/K6 | N16: 0 | O16: =N16/N6 | T16: =F16 | U16: =I16 | V16: =I16 | W16: =IF(ISERROR(Q30),"",IF(Q30=0,"",Q30)) | X16: =MIN(T16:W16) | Y16: =MAX(T16:W16) | AA16: =IF(X16=Y16,TEXT(X16,"$0.00;;-"),CONCATENATE(TEXT(X16,"$0.00;;-"),"–",TEXT(Y16,"$0.00;;-"))) | AB16: =AVERAGE(T16:W16)
D17: Total Expenses | E17: =SUM(E10:E16) | F17: =SUM(F10:F15) | H17: =SUM(H10:H16) | I17: =SUM(I10:I15) | K17: =SUM(K10:K16) | L17: =SUM(L9:L15) | N17: =SUM(N10:N16) | O17: =N17/N6 | T17: =F17 | U17: =I17 | V17: =L17 | W17: =IF(ISERROR(Q31),"",IF(Q31=0,"",Q31)) | X17: =MIN(T17:W17) | Y17: =MAX(T17:W17) | AA17: =IF(X17=Y17,TEXT(X17,"$0.00;;-"),CONCATENATE(TEXT(X17,"$0.00;;-"),"–",TEXT(Y17,"$0.00;;-"))) | AB17: =AVERAGE(T17:W17)
T18: =IF(H32=0,"",H32) | U18: =IF(K32=0,"",K32) | V18: =IF(N32=0,"",N32) | W18: =IF(ISERROR(Q32),"",IF(Q32=0,"",Q32)) | X18: =MIN(T18:W18) | Y18: =MAX(T18:W18) | AA18: =IF(X18=Y18,TEXT(X18,"$0.00;;-"),CONCATENATE(TEXT(X18,"$0.00;;-"),"–",TEXT(Y18,"$0.00;;-"))) | AB18: =AVERAGE(T18:W18)
T19: =IF(H33=0,"",H33) | U19: =IF(K33=0,"",K33) | V19: =IF(N33=0,"",N33) | W19: =IF(ISERROR(Q33),"",IF(Q33=0,"",Q33)) | X19: =MIN(T19:W19) | Y19: =MAX(T19:W19) | AA19: =IF(X19=Y19,TEXT(X19,"$0.00;;-"),CONCATENATE(TEXT(X19,"$0.00;;-"),"–",TEXT(Y19,"$0.00;;-"))) | AB19: =AVERAGE(T19:W19)
T20: =IF(H34=0,"",H34) | U20: =IF(K34=0,"",K34) | V20: =IF(N34=0,"",N34) | W20: =IF(ISERROR(Q34),"",IF(Q34=0,"",Q34)) | X20: =MIN(T20:W20) | Y20: =MAX(T20:W20) | AA20: =IF(X20=Y20,TEXT(X20,"$0.00;;-"),CONCATENATE(TEXT(X20,"$0.00;;-"),"–",TEXT(Y20,"$0.00;;-"))) | AB20: =AVERAGE(T20:W20)
T21: =IF(H35=0,"",H35) | U21: =IF(K35=0,"",K35) | V21: =IF(N35=0,"",N35) | W21: =IF(ISERROR(Q35),"",IF(Q35=0,"",Q35)) | X21: =MIN(T21:W21) | Y21: =MAX(T21:W21) | AA21: =IF(X21=Y21,TEXT(X21,"$0.00;;-"),CONCATENATE(TEXT(X21,"$0.00;;-"),"–",TEXT(Y21,"$0.00;;-"))) | AB21: =AVERAGE(T21:W21)
T22: =IF(H36=0,"",H36) | U22: =IF(K36=0,"",K36) | V22: =IF(N36=0,"",N36) | W22: =IF(ISERROR(Q36),"",IF(Q36=0,"",Q36)) | X22: =MIN(T22:W22) | Y22: =MAX(T22:W22) | AA22: =IF(X22=Y22,TEXT(X22,"$0.00;;-"),CONCATENATE(TEXT(X22,"$0.00;;-"),"–",TEXT(Y22,"$0.00;;-"))) | AB22: =AVERAGE(T22:W22)
T23: =IF(H37=0,"",H37) | U23: =IF(K37=0,"",K37) | V23: =IF(N37=0,"",N37) | W23: =IF(ISERROR(Q37),"",IF(Q37=0,"",Q37)) | X23: =MIN(T23:W23) | Y23: =MAX(T23:W23) | AA23: =IF(X23=Y23,TEXT(X23,"$0.00;;-"),CONCATENATE(TEXT(X23,"$0.00;;-"),"–",TEXT(Y23,"$0.00;;-"))) | AB23: =AVERAGE(T23:W23)
T24: =IF(H38=0,"",H38) | U24: =IF(K38=0,"",K38) | V24: =IF(N38=0,"",N38) | W24: =IF(ISERROR(Q38),"",IF(Q38=0,"",Q38)) | X24: =MIN(T24:W24) | Y24: =MAX(T24:W24) | AA24: =IF(X24=Y24,TEXT(X24,"$0.00;;-"),CONCATENATE(TEXT(X24,"$0.00;;-"),"–",TEXT(Y24,"$0.00;;-"))) | AB24: =AVERAGE(T24:W24)
T25: =IF(H39=0,"",H39) | U25: =IF(K39=0,"",K39) | V25: =IF(N39=0,"",N39) | W25: =IF(Q39=0,"",Q39) | X25: =MIN(T25:W25) | Y25: =MAX(T25:W25) | AA25: =IF(X25=Y25,TEXT(X25,"$0.00;;-"),CONCATENATE(TEXT(X25,"$0.00;;-"),"–",TEXT(Y25,"$0.00;;-"))) | AB25: =AVERAGE(T25:W25)
T26: =IF(I38=0,"",I38) | U26: =IF(L38=0,"",L38) | V26: =IF(O38=0,"",O38) | W26: =IF(R38=0,"",R38) | X26: =MIN(T26:W26) | Y26: =MAX(T26:W26) | AA26: =IF(X26=Y26,TEXT(X26,"0%;-"),CONCATENATE(TEXT(X26,"0%;-"),"–",TEXT(Y26,"0%;-")))
T28: =G42 | U28: =J42 | V28: =M42 | W28: =P42 | X28: =MIN(T28:W28) | Y28: =MAX(T28:W28) | AA28: =IF(X28=Y28,TEXT(X28,"$#,##0"),CONCATENATE(TEXT(X28,"$#,##0"),"–",TEXT(Y28,"$#,##0"))) | AB28: =IF(SUM(T28:W28)=0,0,ROUND(AVERAGE(T28:W28),0))
T29: =G43 | U29: =J43 | V29: =M43 | W29: =P43 | X29: =MIN(T29:W29) | Y29: =MAX(T29:W29) | AA29: =IF(X29=Y29,TEXT(X29,"$0.00;;-"),CONCATENATE(TEXT(X29,"$0.00;;-"),"–",TEXT(Y29,"$0.00;;-"))) | AB29: =IF(SUM(T29:W29)=0,0,ROUND(AVERAGE(T29:W29),2))
T30: =G44 | U30: =J44 | V30: =M44 | W30: =P44 | X30: =MIN(T30:W30) | Y30: =MAX(T30:W30) | AA30: =IF(X30=Y30,TEXT(X30,"0%;-"),CONCATENATE(TEXT(X30,"0%;-"),"–",TEXT(Y30,"0%;-"))) | AB30: =IF(SUM(T30:W30)=0,0,ROUND(AVERAGE(T30:W30),3))

Sheet OECC
E2: OPERATING EXPENSE COMPARISON AND CONCLUSION | O2: =LA!C5
C3: =LA!C5 | F3: Expense Comps
E4: Expense Item | F4: Range | G4: Average | H4: 2016 | I4: 2017 | J4: Forecast | K4: Comments
E5: Real Estate Taxes | F5: =CED!AA10 | G5: =CED!AB10 | H5: =HOA!M24 | I5: =HOA!P24 | J5: 38203 | K5: Taxes were previously concluded in the tax section of this report.
H6: =H5/$O$2 | I6: =I5/$O$2 | J6: =J5/$O$2
E8: Insurance | F8: =CED!AA11 | G8: =CED!AB11 | H8: =HOA!M25 | I8: =HOA!P25 | J8: =J9*C3 | K8: We apply an insurance expece for the subject near the middle of the comparables.
H9: =H8/$O$2 | I9: =I8/$O$2 | J9: 1.25
E11: Utilities | F11: =CED!AA12 | G11: =CED!AB12 | H11: =HOA!M27 | I11: =HOA!P27 | J11: =J12*C3 | K11: Comparables indicate a range of utility expenses between $1.50 and $2.23 per square foot. We apply a utilities expense for the subject near the middle of the range of comparables.
H12: =H11/$O$2 | I12: =I11/$O$2 | J12: 1.5
E14: CAM Repairs and Maintenance | F14: =CED!AA13 | G14: =CED!AB13 | H14: =HOA!M28 | I14: =HOA!P28 | J14: =J15*C3 | K14: We conclude to an expense near the average of the comparables.
H15: =H14/$O$2 | I15: =I14/$O$2 | J15: 1.5
E17: Management | F17: N/R | G17: N/R | H17: =HOA!M30 | I17: =HOA!P30 | J17: =PF!G9*0.03 | K17: Typical management expenses for similar properties range from 2% to 5% of EGI. We conclude to an expense near 3% of EGI, which is within the range of the comparables on a PSF basis.
H18: =H17/$O$2 | I18: =I17/$O$2 | J18: =J17/C3
E20: Replacement Reserves | H20: =H21/NRA | I20: =I21/NRA | J20: 0
F21: 0 | G21: 0 | H21: 0 | I21: 0 | J21: =J20/$O$2
E23: Total Operating Expenses | H23: =SUM(H5,H8,H11,H14,H17,H20) | I23: =SUM(I5,I8,I11,I14,I17,I20) | J23: =SUM(J5,J8,J11,J14,J17)
E24: Total Operating Expenses Per SF | H24: =SUM(H6,H9,H12,H15,H18,H21) | I24: =SUM(I6,I9,I12,I15,I18,I21) | J24: =J23/C3
H28: =H17/HOA!M22 | I28: =I17/HOA!P22
H29: =J23
H30: 0
H31: =SUM(H29:H30)
H32: 0
H34: =SUM(H31:H32) | I34: =J17 | J34: =I34/H34

Sheet PF
E2: PRO FORMA OPERATIONS
E3: Income | G3: $ | H3: Per SF
E4: Gross Potential Rent | G4: ='Income Approach'!D37 | H4: =G4/LA!C5
E5: Expense Recoveries | G5: 0 | H5: =G5/LA!C5
E6: Total Potential Gross Income | G6: =SUM(G4:G5) | H6: =G6/LA!C5
E7: Less Vacancy/Collection Loss | F7: ='Income Approach'!D22 | G7: =-(F7*G6) | H7: =G7/LA!C5
E8: Less Collection Loss | F8: 0 | G8: =-(F8*G6) | H8: =G8/LA!C5
E9: Effective Gross Income (EGI) | G9: =SUM(G6:G8) | H9: =G9/LA!C5
E10: Expenses
E11: Real Estate Taxes | G11: 0 | H11: =G11/LA!$C$5
E12: Insurance | G12: 0 | H12: =G12/LA!$C$5
E13: Utilities | G13: 0 | H13: =G13/LA!$C$5
E14: CAM Repairs and Maintenance | G14: 0 | H14: =G14/LA!$C$5
E15: Management | G15: 0 | H15: =G15/LA!$C$5
E16: Replacement Reserves | G16: =H16*'Property Info'!B6 | H16: 0.25
E17: Total Expenses | F17: =G17/G9 | G17: =SUM(G11:G16) | H17: =G17/LA!C5
E18: Net Operating Income (NOI) | G18: =G9-G17 | H18: =G18/LA!C5

Sheet Cap Rate Lease-Up
B2: MARKET DERIVED CAPITALIZATION RATE SUMMARY
B14: Low | M14: =ROUND(MIN(M4:M13),4)
B15: High | M15: =ROUND(MAX(M4:M13),4)
B16: Median | M16: =ROUND(MEDIAN(M4:M13),4)
B17: Average | M17: =ROUND(AVERAGE(M4:M12),4)
B18: Appraiser's Concluded Range | M18: 6.00% - 6.50%
O20: Third Party Surveys - Capitalization Rates
O21: Category | P21: CoStar | Q21: CoStar | R21: CoStar
O22: Date of Survey | P22: 1/1/2019-6/30/2020 | Q22: 1/1/2019-6/30/2020 | R22: 1/1/2019-6/30/2020
O23: Market | P23: Adams County | Q23: North Metro Denver | R23: Denver CBSA
O24: Property Type | P24: Industrial - 10,000 SF - 50,000 SF | Q24: Industrial - 10,000 SF - 50,000 SF | R24: Industrial - 10,000 SF - 50,000 SF
O25: Range Average | P25: 4.0% -8.4% | Q25: 4.0% - 10.0% | R25: 4.0% - 11.5%
O26: Average | P26: 0.064 | Q26: 0.066 | R26: 0.069
T40: SUMMARY CAPITALIZATION RATE AND CONCLUSION
T41: Method | U41: Capitalization Rate
T42: Market Extraction | U42: =M18
T43: Investor Surveys | U43: 6.00% - 6.50%
T44: Market Participants | U44: =iaOARBrokers
T45: Band of Investment | U45: 0.075
T46: DCR | U46: =iaOARDCR
T47: Primary Weight | U47: Market Extraction
T48: Secondary Weight | U48: Investor Surveys
T49: Capitalization Rate Conclusion | U49: 0.0675
T53: LEASE-UP COSTS
T54: Method | U54: Capitalization Rate
T55: Preliminary Value | U55: ='IA Values'!G13
T56: Less: Lost Income | U56: 166157
T57: Less: Tenant Finish | U57: =iaOARBrokers
T58: Less: Leasing Commissions | U58: 35890
T59: Total | U59: =SUM(U56:U58)
T60: Entrepreneurial Profit | U60: =U59*0.1
T61: Total Deductions | U61: =SUM(U59,U60)
T62: "As Is" Value | U62: =U55-U61
T63: Rounded Value | U63: 1350000

Sheet IA Values
K2: ='Property Info'!B6
E3: DIRECT CAPITALIZATION METHOD VALUE CONCLUSION - AS IS
E4: Net Operating Income (NOI) | G4: ='Income Approach'!D47 | H4: =G4/K2
E5: 0.0025 | G5: Value | H5: $/SF
E6: Based on Low-Range of 7.25% | G6: =G4/('Cap Rate Lease-Up'!U49-0.0025) | H6: =G6/K2
E7: Based on Most Probable Range of 7.50% | G7: =G4/'Cap Rate Lease-Up'!U49 | H7: =G7/K2
E8: Based on High-Range of 7.75% | G8: =G4/('Cap Rate Lease-Up'!U49+0.0025) | H8: =G8/K2
E10: =IF(SUM(G11:G11)=0,"HIDE THIS ROW IF NO DEFERRED MAINTENANCE", "Indicated Value") | G10: =G7
E11: =IF(G11=0,"HIDE THIS ROW IF NO DEFERRED MAINTENANCE","Less: Deferred Maintenance") | G11: =-caDeferredMaint
E12: =IF(G11=0,"Reconciled Value","Reconciled Value - Adjusted") | G12: =SUM(G10:G11) | H12: =G12/K2
E13: 5000 | G13: =ROUND((G12/E13),0)*E13 | H13: =G13/K2
A16: DEDUCTIONS TO REACH AN AS IS VALUE
A17: Indicated Value UPON COMPLETION | B17: =G13
A18: Remaining Capital Improvements | B18: -354600
A19: Entrepreneurial Incentive (15% of Total Construction Costs) | B19: -59100
A20: =IF(B21=0,"HIDE THIS ROW IF NO DEFERRED MAINTENANCE", "Indicated Value") | B20: 0
A21: =IF(B21=0,"HIDE THIS ROW IF NO DEFERRED MAINTENANCE","Less: Deferred Maintenance") | B21: 0
A22: Indicated Value AS IS | B22: =SUM(B17:B19)
A23: Indicated Value AS IS | B23: =MROUND(B22,5000)
A24: Per SF | B24: =B23/3112

Sheet Income Approach
A2: Subject's Total SF Area | B2: =FE!C14 | C2: ←
G3: POTENTIAL GROSS RENTAL INCOME
A4: Use only if comparing contract to market rent. Hide for owner-user buildings→ | H4: Area | J4: Contract Rent | M4: Market Rent
G5: Tenant | H5: Total (SF) | J5: $/SF | K5: Annl. Rent | M5: $/SF | N5: Annl. Rent
G6: =LA!C3 | H6: =FE!C14 | J6: =LA!C11 | K6: =LA!C10 | M6: =C11 | N6: =H6*M6
A8: PGRI – MARKET RENTS
A9: Space Type | B9: SF | C9: Rent PSF | D9: PGRI
A11: ='Property Info'!B15 | B11: 3320 | C11: 121.5 | D11: =C11*B11
A13: VACANCY AND COLLECTION LOSS
A14: Source | D14: Rate
A15: CoStar - Denver CBSA - Industrial 20,000 SF - 50,000 SF- Q1 2019-Q2 2020 | D15: 0.043
A16: CoStar - Adams County - Industrial - Q1 2019-Q2 2020 | D16: 0.07
A21: Range | D21: =TEXT(MIN(D15:D20),"0.00%")&" to "&TEXT(MAX(D15:D20),"0.00%")
A22: Concluded Overall Vacancy Rate | D22: 0.06 | F22: ←Change
A24: EXPENSES IN TIME OF VACANCY
A25: Expense | C25: PSF | D25: Total
A26: Real Estate Taxes | C26: =D26/$B$11 | D26: 112047.03 | F26: ← | G26: Actual
A27: Insurance | C27: 1.5 | D27: =C27*$B$2 | F27: ← | G27: Estimated
A28: Utilities | C28: 1.75 | D28: =C28*$B$2 | F28: ← | G28: Estimated
A29: CAM Repairs and Maintenance | C29: 2.5 | D29: =C29*$B$2 | F29: ← | G29: Estimated
A30: Management | C30: =D30/$B$11 | D30: =D42*0.03 | F30: ← | G30: 3% EGI
A31: Total | C31: =D31/B2 | D31: =SUM(D26:E30)
A32: Multiplied by Vacancy Factor of | B32: =D22 | C32: =$B$41*C31 | D32: =$B$41*D31
A33: Divided by EGI | D33: =D32/D42
A35: PRO FORMA OPERATING STATEMENT
A36: Category | C36: Projected Expenses | D36: Projected Income | E36: PSF
A37: Potential Gross Rental Income (PGRI) | D37: =+D11 | E37: =+D37/$B$2
A38: Plus: Other Income | D38: 0 | E38: =+D38/$B$2
A39: Plus: Pass-Through Income | D39: 0 | E39: =+D39/$B$2
A40: Total Potential Gross Rental Income | D40: =SUM(D37:D39) | E40: =+D40/$B$2
A41: Less: Market Vacancy | B41: =D22 | C41: =+B41*D40*-1 | E41: =+C41/$B$2
A42: Effective Gross Income (EGI) | D42: =+D40+C41 | E42: =+D42/$B$2
A43: Fixed Expenses
A44: Owner's Expenses | B44: 0.01 | C44: =+B44*D42*-1 | E44: =+C44/$B$2
A45: Operating Expense Recovery Loss During Vacancy | B45: =D33 | C45: =-D32 | E45: =+C45/$B$2
A46: Total Expenses | C46: =SUM(C44:C45) | E46: =+C46/$B$2
A47: Net Operating Income | D47: =+D42+C46 | E47: =+D47/$B$2 | S47: Reconciled OAR | T47: 0.11 | U47: ←
S48: Sensitivity | T48: 0.0025 | U48: ←
A49: Third Party Surveys - Capitalization Rates
A50: Category | C50: CoStar | D50: CoStar | S50: Value Indications
A51: Date of Survey | C51: 01/01/2019-06/30/2020 | D51: 01/01/2019-06/30/2020 | S51: Category | T51: Value Range
A52: Market | C52: Denver CBSA | D52: Adams County | S52: Net Operating Income | T52: =+$D$47 | U52: =+$D$47 | V52: =+$D$47
A53: Property Type | C53: Industrial/Flex | D53: Industrial/Flex | S53: Capitalization Rate | T53: =U53-T48 | U53: =T47 | V53: =U53+T48
A54: Range Average | C54: 4.0% - 12.0% | D54: 4.0% - 11.0% | F54: ←Change | S54: Value Indication | T54: =+T52/T53 | U54: =+U52/U53 | V54: =+V52/V53
A55: Average | C55: 0.07 | D55: 0.068 | F55: ←Change | S55: Rounded | T55: =MROUND(T54,5000) | U55: =MROUND(U54,5000) | V55: =MROUND(V54,5000)
A56: Capitalization Rate Conclusion | D56: 0.065 | F56: =D56*100
A58: DIRECT CAPITALIZATION METHOD VALUE CONCLUSION | T58: psf | U58: =U55/B2
A59: Net Operating Income (NOI) | C59: =D47 | D59: =C59/B2
A60: 0.0025 | C60: Value | D60: $/SF
A61: =A72 | C61: =C59/(D56-0.0025) | D61: =C61/B2
A62: =A70 | C62: =C59/D56 | D62: =C62/B2
A63: =A71 | C63: =C59/(D56+0.0025) | D63: =C63/B2
A64: Reconciled Value | C64: =C62 | D64: =C64/B2
A65: 5000 | C65: =ROUND((C64/A65),0)*A65 | D65: =C65/B2
A69: Do not overwright
A70: =CONCATENATE("Based on Most Probable Range of ", FIXED(F56, 2), "%")
A71: =CONCATENATE("Based on High-Range of ", FIXED(F56+0.25, 2), "%")
A72: =CONCATENATE("Based on Low-Range of ", FIXED(F56-0.25, 2), "%")

Sheet Resources
A1: APPRAISAL RESOURCE DIRECTORY
A2: ="Active Property: "&'Property Info'!B16&" | City / Area: "&'Property Info'!B17&" | County: "&'Property Info'!B18
A3: Tip: Filter or sort the Priority column — rows marked ★ Active match the current property's city/county. Regional rows apply to all properties.
A5: Priority | B5: Municipality / Area | C5: Category | D5: Resource Name | E5: URL | F5: Description
A6: =IF(OR(ISNUMBER(SEARCH(LEFT('Property Info'!$B$17,MAX(1,FIND(",",'Property Info'!$B$17&",")-1)),B6)),ISNUMBER(SEARCH('Property Info'!$B$18,B6))),"★ Active",IF(B6="REGIONAL / ALL MUNICIPALITIES","Regional","–")) | B6: Adams County (Unincorporated) | C6: Property Assessment | D6: Assessor Property Lookup | E6: https://adcogov.org/property-look | F6: Primary parcel/property search tool for all of Adams County
A7: =IF(OR(ISNUMBER(SEARCH(LEFT('Property Info'!$B$17,MAX(1,FIND(",",'Property Info'!$B$17&",")-1)),B7)),ISNUMBER(SEARCH('Property Info'!$B$18,B7))),"★ Active",IF(B7="REGIONAL / ALL MUNICIPALITIES","Regional","–")) | B7: Adams County (Unincorporated) | C7: Property Assessment | D7: Assessor GIS QuickSearch | E7: https://gisapp.adcogov.org/quicksearch/ | F7: Address or parcel-based search with map
A8: =IF(OR(ISNUMBER(SEARCH(LEFT('Property Info'!$B$17,MAX(1,FIND(",",'Property Info'!$B$17&",")-1)),B8)),ISNUMBER(SEARCH('Property Info'!$B$18,B8))),"★ Active",IF(B8="REGIONAL / ALL MUNICIPALITIES","Regional","–")) | B8: Adams County (Unincorporated) | C8: Property Assessment | D8: Assessor Main Page | E8: https://adcogov.org/assessor | F8: Assessor office info and resources
A9: =IF(OR(ISNUMBER(SEARCH(LEFT('Property Info'!$B$17,MAX(1,FIND(",",'Property Info'!$B$17&",")-1)),B9)),ISNUMBER(SEARCH('Property Info'!$B$18,B9))),"★ Active",IF(B9="REGIONAL / ALL MUNICIPALITIES","Regional","–")) | B9: Adams County (Unincorporated) | C9: Property Assessment | D9: NOV / Online Appeals Portal | E9: https://assessor.adcogov.org/ | F9: Notice of Valuation and assessment appeals
A10: =IF(OR(ISNUMBER(SEARCH(LEFT('Property Info'!$B$17,MAX(1,FIND(",",'Property Info'!$B$17&",")-1)),B10)),ISNUMBER(SEARCH('Property Info'!$B$18,B10))),"★ Active",IF(B10="REGIONAL / ALL MUNICIPALITIES","Regional","–")) | B10: Adams County (Unincorporated) | C10: Property Assessment | D10: Public Data Download | E10: https://assessornovs.adcogov.org/adamscountynovs | F10: Weekly-updated bulk assessor data download
A11: =IF(OR(ISNUMBER(SEARCH(LEFT('Property Info'!$B$17,MAX(1,FIND(",",'Property Info'!$B$17&",")-1)),B11)),ISNUMBER(SEARCH('Property Info'!$B$18,B11))),"★ Active",IF(B11="REGIONAL / ALL MUNICIPALITIES","Regional","–")) | B11: Adams County (Unincorporated) | C11: Property Tax / Treasurer | D11: Treasurer Division | E11: https://adamscountyco.gov/our-county/elected-officials/treasurer-public-trustee/treasurer-division/ | F11: Main treasurer page
A12: =IF(OR(ISNUMBER(SEARCH(LEFT('Property Info'!$B$17,MAX(1,FIND(",",'Property Info'!$B$17&",")-1)),B12)),ISNUMBER(SEARCH('Property Info'!$B$18,B12))),"★ Active",IF(B12="REGIONAL / ALL MUNICIPALITIES","Regional","–")) | B12: Adams County (Unincorporated) | C12: Property Tax / Treasurer | D12: Online Tax Payment | E12: https://adcotax.com/treasurer/web/login.jsp | F12: Pay property taxes online
A13: =IF(OR(ISNUMBER(SEARCH(LEFT('Property Info'!$B$17,MAX(1,FIND(",",'Property Info'!$B$17&",")-1)),B13)),ISNUMBER(SEARCH('Property Info'!$B$18,B13))),"★ Active",IF(B13="REGIONAL / ALL MUNICIPALITIES","Regional","–")) | B13: Adams County (Unincorporated) | C13: Property Tax / Treasurer | D13: Property Tax Inquiry | E13: https://adamsil.devnetwedge.com/ | F13: Look up tax balances and payment history
A14: =IF(OR(ISNUMBER(SEARCH(LEFT('Property Info'!$B$17,MAX(1,FIND(",",'Property Info'!$B$17&",")-1)),B14)),ISNUMBER(SEARCH('Property Info'!$B$18,B14))),"★ Active",IF(B14="REGIONAL / ALL MUNICIPALITIES","Regional","–")) | B14: Adams County (Unincorporated) | C14: Property Tax / Treasurer | D14: Taxing Authorities / Mill Levy | E14: https://adamscountyco.gov/our-county/elected-officials/treasurer-public-trustee/treasurer-division/property-tax-information/taxing-authorities/ | F14: Mill levy lookup by taxing district
A15: =IF(OR(ISNUMBER(SEARCH(LEFT('Property Info'!$B$17,MAX(1,FIND(",",'Property Info'!$B$17&",")-1)),B15)),ISNUMBER(SEARCH('Property Info'!$B$18,B15))),"★ Active",IF(B15="REGIONAL / ALL MUNICIPALITIES","Regional","–")) | B15: Adams County (Unincorporated) | C15: Property Tax / Treasurer | D15: DOLA Division of Property Taxation | E15: https://dpt.colorado.gov/locality/adams-county-treasurer | F15: Colorado state-level property tax data for Adams County
A16: =IF(OR(ISNUMBER(SEARCH(LEFT('Property Info'!$B$17,MAX(1,FIND(",",'Property Info'!$B$17&",")-1)),B16)),ISNUMBER(SEARCH('Property Info'!$B$18,B16))),"★ Active",IF(B16="REGIONAL / ALL MUNICIPALITIES","Regional","–")) | B16: Adams County (Unincorporated) | C16: Property Tax / Treasurer | D16: DOLA Mill Levy Public Info (HB24-1302) | E16: https://dlg.colorado.gov/hb24-1302-mill-levy-public-information | F16: Statewide mill levy transparency portal
A17: =IF(OR(ISNUMBER(SEARCH(LEFT('Property Info'!$B$17,MAX(1,FIND(",",'Property Info'!$B$17&",")-1)),B17)),ISNUMBER(SEARCH('Property Info'!$B$18,B17))),"★ Active",IF(B17="REGIONAL / ALL MUNICIPALITIES","Regional","–")) | B17: Adams County (Unincorporated) | C17: Deed / Title Records | D17: Clerk & Recorder Recording Page | E17: https://adcogov.org/recording | F17: Official recording office
... A302: =IF(OR(ISNUMBER(SEARCH(LEFT('Property Info'!$B$17,MAX(1,FIND(",",'Property Info'!$B$17&",")-1)),B302)),ISNUMBER(SEARCH('Property Info'!$B$18,B302))),"★ Active",IF(B302="REGIONAL / ALL MUNICIPALITIES","Regional","–")) | B302: REGIONAL / ALL MUNICIPALITIES | C302: School Districts | D302: Jefferson County Public Schools | E302: https://www.jeffcopublicschools.org/ | F302: Serves Westminster and Arvada (Jefferson Co. portions)
